Workbook

Sheet Model
B1: Model Structure | D1: All the key assumptions and results are are on the control panel.
D2: Changing an assumption on the control panel will change the results on the individual worksheets.
D3: To change a key assumption, change it on the control panel not on the individual worksheets
B5: Control panel | D5: Sales | F5: Cost of goods | H5: Operating costs | J5: Project Financials | L5: Lee vs Lor | N5: Licensor financial status
J6: For total project calculates | L6: For Licensee and Licensor calculates | N6: For Licensor only calculates
B7: Sales forecast
B8: Market share volume | D8: Calculates sales | J8: Sales | L8: Sales
B9: Price premium
B10: Share of voice
B12: Cost of goods - who manufactures? | F12: Calculates cost of goods | J12: Cost of goods | L12: Cost of goods
B13: Licensor manufacture | F13: in each scenario
B14: Zero capital spend
B15: Profit mark-up on cost
B16: Licensee manufacture
B17: Capital spend
B18: Lower cost of goods
B20: R & D costs - who pays? | H20: Calculates R & D costs | J20: R&D costs | L20: R&D costs
B21: Formulation and scale up
B22: Clinical trials
B25: Sales and marketing | H25: Calculates S & P costs | J25: S&P and other costs | L25: S&P and other costs
B26: Salesforce cost allocation | H26: and other costs
B27: Direct promotion costs | H27: distribution, admin, etc
B29: Licence fees and royalty | L29: Deal payments | N29: Lor year end cash balance
B30: Signature fee
B31: Milestone payments
B32: Royalty
J34: Calculates Project NPV and IRR | L34: Calculates Lee and Lor NPV and IRR
B36: NPV summary for Lee and Lor

Sheet Control
B2: CONTROL PANEL | F2: Key assumptions shown in red in yellow cells. Changes to these cells with change the results of the model | S2: Results are shown in blue | Y2: 2008
B4: SALES FORECAST | M4: 0 | N4: =M4+1 -> 1 | O4: 2 | P4: =O4+1 -> 3 | Q4: =P4+1 -> 4 | R4: =Q4+1 -> 5 | S4: =R4+1 -> 6 | T4: =S4+1 -> 7 | U4: =T4+1 -> 8 | V4: =U4+1 -> 9 | W4: =V4+1 -> 10 | ... Y4: =X4+1 -> 12
C5: Number of competing products (incl. prolutamide) Enter 2 or 3 | I5: 2 | K5: Yr 5 Mkt Sh | L5: Sales $m | M5: =Y2+1 -> 2009 | N5: =M5+1 -> 2010 | O5: =N5+1 -> 2011 | P5: =O5+1 -> 2012 | Q5: =P5+1 -> 2013 | R5: =Q5+1 -> 2014 | S5: =R5+1 -> 2015 | T5: =S5+1 -> 2016 | U5: =T5+1 -> 2017 | ... Y5: =X5+1 -> 2021
C6: Prolutamide TTP advantage versus Janssen product? YES = 1, NO= 0 | I6: 1 | K6: =Sales!G27 -> 0.38333333 | L6: US | P6: =Sales!J38 -> 71.165835 | Q6: =Sales!K38 -> 390.65902 | R6: =Sales!L38 -> 676.77395 | S6: =Sales!M38 -> 1145.6168 | T6: =Sales!N38 -> 1475.4927 | U6: =Sales!O38 -> 1785.3692 | V6: =Sales!P38 -> 2127.5686 | W6: =Sales!Q38 -> 2404.2916 | ... Y6: =Sales!S38 -> 2901.8369
C7: Price at parity / below / above: target price Enter: 0%,-30%,30% | H7: US | I7: 0 | K7: =Sales!G28 -> 0.40333333 | L7: Non US | P7: =Sales!J39 -> 0 | Q7: =Sales!K39 -> 53.555488 | R7: =Sales!L39 -> 363.58601 | S7: =Sales!M39 -> 713.74853 | T7: =Sales!N39 -> 1015.2856 | U7: =Sales!O39 -> 1280.1789 | V7: =Sales!P39 -> 1507.7218 | W7: =Sales!Q39 -> 1733.2251 | ... Y7: =Sales!S39 -> 2070.6781
C8: Price at parity / below / above: target price Enter: 0%,-30%,30% | H8: Non-US | I8: 0 | L8: Total | P8: =P6+P7 -> 71.165835 | Q8: =Q6+Q7 -> 444.21451 | R8: =R6+R7 -> 1040.36 | S8: =S6+S7 -> 1859.3653 | T8: =T6+T7 -> 2490.7782 | U8: =U6+U7 -> 3065.548 | V8: =V6+V7 -> 3635.2904 | W8: =W6+W7 -> 4137.5167 | ... Y8: =Y6+Y7 -> 4972.515
B9: COST OF GOODS | O9: R&D
C10: Will the Licensee manufacture inhouse? Enter 1 for YES or 0 for NO | I10: 0 | L10: NPV of savings to Licensee | N10: =COG!J70 -> 0 | U10: Additional patients for bicalutamide studies? Enter 1 for YES or 0 for NO | V10: 0
C11: If YES, capital expenditure by Licensee? Enter 15 for $15m or 30 for $30m | I11: 30 | L11: Licensee COG + plus royalty in | M11: 2021 | N11: ='Lee & Lor'!Q61 -> 0.1922494
C12: If NO, profit mark-up % applied by Licensor on cost of supply from CMO | I12: 0.25 | O12: IP COSTS | S12: US | T12: Non-US
B13: SALES AND MARKETING COSTS | I13: Yr 1-5 | J13: Yr 6-10 | L13: Full time | M13: 1st detail | O13: Royalties payable by Licensor to University | S13: 0.04 | T13: 0.04
C14: % time Licensee salesforce promote prolutamide | H14: US | I14: 1 | J14: 1 | L14: 1 | M14: 0.65
C15: % time Licensee salesforce promote prolutamide | H15: Non-US | I15: 1 | J15: 1 | L15: 1 | M15: 0.65
C16: US co-commercialisation profit share to Licensor Enter % | H16: US | I16: 0.5
C17: If US co-commercialisation enter fee per call paid to Licensor | H17: US | I17: 500 | R17: Net gain/(loss) to Licensee of co-commercialisation (= (gain)/loss to Licensor) NPV $m | S17: ='S&M'!G88 -> 432.36993
B19: ELEMENTS OF LICENSING DEAL | G19: Headline value excluding R&D and royalties | L19: =L22+R31+L36 -> 800 | M19: =L19/Y8 -> 0.16088438 | N19: % of peak sales
C20: R & D costs
D21: Licensee share of R&D costs | F21: % Lee pays | G21: Cost $m | I21: Other Financial Deal Terms | L21: $m
D22: Manufacturing scale-up | F22: 0.5 | G22: 48 | I22: Signature fee | L22: 150 | M22: =M5 -> 2009
D23: Phase 3 studies | F23: 1 | G23: ='R&D'!V20 -> 753.13338 | L23: Post chemo CRPC | N23: HSPC | P23: Non chemo CRPC | R23: Total
D24: Phase 4 studies | F24: 1 | G24: ='R&D'!V21 -> 69.981392 | I24: First patient dosed in clinical | L24: 0 | N24: 25 | O24: 2014 | P24: 25 | Q24: 2010 | R24: =L24+N24+P24 -> 50
D25: Non prostate cancer studies | F25: 0.5 | G25: ='R&D'!V28 -> 30.58856 | I25: Acceptance of filing | K25: US | L25: 10 | M25: 2010 | N25: 25 | O25: 2014 | P25: 10 | Q25: 2012 | R25: =L25+N25+P25 -> 45
E26: Total cost | G26: =SUM(G22:G25) -> 901.70333 | K26: Europe | L26: 5 | M26: 2014 | N26: 20 | O26: 2014 | P26: 5 | Q26: 2012 | R26: =L26+N26+P26 -> 30
D27: Cost to Licensee $m | G27: ='R&D'!E37 -> 862.40905 | K27: Japan | L27: 5 | M27: 2014 | N27: 10 | O27: 2014 | P27: 5 | Q27: 2013 | R27: =L27+N27+P27 -> 20
D28: Cost to Licensor $m | G28: ='R&D'!E38 -> 39.29428 | I28: Approval of MA | K28: US | L28: 40 | M28: 2014 | N28: 65 | O28: 2014 | P28: 40 | Q28: 2012 | R28: =L28+N28+P28 -> 145
K29: Europe | L29: 15 | M29: 2014 | N29: 30 | O29: 2014 | P29: 15 | Q29: 2013 | R29: =L29+N29+P29 -> 60
K30: Japan | L30: 15 | M30: 2014 | N30: 20 | O30: 2014 | P30: 15 | R30: =L30+N30+P30 -> 50
C31: Royalty payment by Licensee to Lor | K31: Total | L31: =SUM(L24:L30) -> 90 | N31: =SUM(N24:N30) -> 195 | P31: =SUM(P24:P30) -> 115 | R31: =L31+N31+P31 -> 400
E32: Sales < x | F32: 400 | G32: 0.1 | I32: Annual sales > $m | K32: 400 | L32: 25
E33: Sales > x < y | F33: 800 | G33: 0.12 | I33: Annual sales > $m | K33: 800 | L33: 50
C34: ` | E34: Sales > y > z | F34: 1200 | G34: 0.14 | I34: Annual sales > $m | K34: 1200 | L34: 75
E35: Sales > z | F35: 1600 | G35: 0.16 | I35: Annual sales > $m | K35: 1600 | L35: 100
L36: =SUM(L32:L35) -> 250
L37: Total | M37: =Y2+1 -> 2009 | N37: =M37+1 -> 2010 | O37: =N37+1 -> 2011 | P37: =O37+1 -> 2012 | Q37: =P37+1 -> 2013 | R37: =Q37+1 -> 2014 | S37: =R37+1 -> 2015 | T37: =S37+1 -> 2016 | U37: =T37+1 -> 2017 | ... Y37: =X37+1 -> 2021
J38: Total development milestones and upfront | L38: =SUM(M38:Y38) -> 535 | M38: =L22 -> 150 | N38: =L25+P24 -> 35 | P38: =P25+P26+P28 -> 55 | Q38: =P27+P29 -> 20 | R38: =N31+L31-L25 -> 275
J39: Total sales milestones | L39: =SUM(M39:Y39) -> 250 | M39: =IF(AND(M$8>=$K32,L$8<$K32),$L32,0)+IF(AND(M$8>=$K33,L$8<$K33),$L33,0)+IF(AND(M$8>=$K34,L$8<$K34),$L34,0)+IF(AND(M$8>=$K35,L$8<$K35),$L35,0) -> 0 | N39: =IF(AND(N$8>=$K32,M$8<$K32),$L32,0)+IF(AND(N$8>=$K33,M$8<$K33),$L33,0)+IF(AND(N$8>=$K34,M$8<$K34),$L34,0)+IF(AND(N$8>=$K35,M$8<$K35),$L35,0) -> 0 | O39: =IF(AND(O$8>=$K32,N$8<$K32),$L32,0)+IF(AND(O$8>=$K33,N$8<$K33),$L33,0)+IF(AND(O$8>=$K34,N$8<$K34),$L34,0)+IF(AND(O$8>=$K35,N$8<$K35),$L35,0) -> 0 | P39: =IF(AND(P$8>=$K32,O$8<$K32),$L32,0)+IF(AND(P$8>=$K33,O$8<$K33),$L33,0)+IF(AND(P$8>=$K34,O$8<$K34),$L34,0)+IF(AND(P$8>=$K35,O$8<$K35),$L35,0) -> 0 | Q39: =IF(AND(Q$8>=$K32,P$8<$K32),$L32,0)+IF(AND(Q$8>=$K33,P$8<$K33),$L33,0)+IF(AND(Q$8>=$K34,P$8<$K34),$L34,0)+IF(AND(Q$8>=$K35,P$8<$K35),$L35,0) -> 25 | R39: =IF(AND(R$8>=$K32,Q$8<$K32),$L32,0)+IF(AND(R$8>=$K33,Q$8<$K33),$L33,0)+IF(AND(R$8>=$K34,Q$8<$K34),$L34,0)+IF(AND(R$8>=$K35,Q$8<$K35),$L35,0) -> 50 | S39: =IF(AND(S$8>=$K32,R$8<$K32),$L32,0)+IF(AND(S$8>=$K33,R$8<$K33),$L33,0)+IF(AND(S$8>=$K34,R$8<$K34),$L34,0)+IF(AND(S$8>=$K35,R$8<$K35),$L35,0) -> 175 | T39: =IF(AND(T$8>=$K32,S$8<$K32),$L32,0)+IF(AND(T$8>=$K33,S$8<$K33),$L33,0)+IF(AND(T$8>=$K34,S$8<$K34),$L34,0)+IF(AND(T$8>=$K35,S$8<$K35),$L35,0) -> 0 | ... Y39: =IF(AND(Y$8>=$K32,X$8<$K32),$L32,0)+IF(AND(Y$8>=$K33,X$8<$K33),$L33,0)+IF(AND(Y$8>=$K34,X$8<$K34),$L34,0)+IF(AND(Y$8>=$K35,X$8<$K35),$L35,0) -> 0
I40: Total Lee milestone payments | L40: =L38+L39 -> 785 | M40: =M38+M39 -> 150 | N40: =N38+N39 -> 35 | O40: =O38+O39 -> 0 | P40: =P38+P39 -> 55 | Q40: =Q38+Q39 -> 45 | R40: =R38+R39 -> 325 | S40: =S38+S39 -> 175 | ... Y40: =Y38+Y39 -> 0
C41: Royalty payments assumed to stop at patent expiry | I41: Total Lee royalty payments | L41: =SUM(M41:W41) -> 2044.2325 | P41: ='Lee & Lor'!H71 -> 7.1165835 | Q41: ='Lee & Lor'!I71 -> 45.305741 | R41: ='Lee & Lor'!J71 -> 121.65039 | S41: ='Lee & Lor'!K71 -> 185.49845 | T41: ='Lee & Lor'!L71 -> 286.52452 | U41: ='Lee & Lor'!M71 -> 378.48769 | V41: ='Lee & Lor'!N71 -> 469.64646 | W41: ='Lee & Lor'!O71 -> 550.00267 | ... Y41: ='Lee & Lor'!Q71 -> 683.6024
C42: Duration of licence to Licensee | L42: =L41/SUM(Q8:V8) -> 0.16307473 | O42: Average royalty rate | P42: =P41/P8 -> 0.1 | Q42: =Q41/Q8 -> 0.10199068 | R42: =R41/R8 -> 0.11693106 | S42: =S41/S8 -> 0.099764393 | T42: =T41/T8 -> 0.11503413 | U42: =U41/U8 -> 0.12346493 | V42: =V41/V8 -> 0.12919091 | W42: =W41/W8 -> 0.13293062 | ... Y42: =Y41/Y8 -> 0.13747619
D43: Licence terminates: expiry data exclusivity / 10 years from launch whichever later | K43: Licensor gets terminal value (enter 0)
D44: Licence continues in perpetuity e.g. while Licensee continues to sell product | K44: Licensee gets terminal value (enter 1) | O44: 1
B45: NPV TO LICENSEE & LICENSOR | F45: Disc rate | G45: 0.12 | H45: NPV | I45: % total | M45: =M22 -> 2009 | N45: =M45+1 -> 2010 | O45: =N45+1 -> 2011 | P45: =O45+1 -> 2012 | Q45: =P45+1 -> 2013 | R45: =Q45+1 -> 2014 | S45: =R45+1 -> 2015 | T45: =S45+1 -> 2016 | U45: =T45+1 -> 2017 | ... Y45: =X45+1 -> 2021
D46: Licensee | H46: ='Lee & Lor'!E31 -> 5710.4626 | I46: =H46/H48 -> 0.60693975 | L46: Licensee project cash flow | M46: ='Lee & Lor'!E30 -> -166.47466 | N46: ='Lee & Lor'!F30 -> -88.840766 | O46: ='Lee & Lor'!G30 -> -82.946869 | P46: ='Lee & Lor'!H30 -> -176.6491 | Q46: ='Lee & Lor'!I30 -> -130.25247 | R46: ='Lee & Lor'!J30 -> -285.40559 | S46: ='Lee & Lor'!K30 -> 216.86724 | T46: ='Lee & Lor'!L30 -> 757.00731 | ... Y46: ='Lee & Lor'!Q30 -> 2032.9029
D47: Licensor | F47: (excl sunk costs) | H47: ='Lee & Lor'!E51 -> 3698.1527 | I47: =H47/H48 -> 0.39306025 | L47: Licensor company cash yr end | M47: ='Lor Financials'!H30 -> 130.31643 | N47: ='Lor Financials'!I30 -> 101.84243 | O47: ='Lor Financials'!J30 -> 73.39543 | P47: ='Lor Financials'!K30 -> 131.93837 | Q47: ='Lor Financials'!L30 -> 151.48344 | R47: ='Lor Financials'!M30 -> 457.44698 | S47: ='Lor Financials'!N30 -> 673.1038
D48: Total | H48: =(H47+H46) -> 9408.6153 | I48: =I47+I46 -> 1 | M48: 57.468 | N48: 107.722 | O48: 70.141 | P48: 71.303 | Q48: 228.79 | R48: 502.68 | S48: 225.86
G49: Check | H49: =Project!E33 -> 9302.5829

Sheet Sales
A1: SALES FORECAST | C1: Assumptions in yellow box from control panel | AL1: Working calculations and notes in grey
B2: Assumptions in red | J2: 1 | K2: 2 | L2: 3 | M2: 4 | N2: 5 | O2: 6 | P2: 7 | Q2: 8 | R2: 9 | S2: 10 | T2: =S2+1 -> 11 | U2: =T2+1 -> 12 | V2: =U2+1 -> 13 | W2: =V2+1 -> 14 | X2: =W2+1 -> 15 | Y2: =X2+1 -> 16 | AA2: Source
B3: Sales forecast | C3: 2005 | D3: 2006 | E3: 2007 | F3: 2008 | G3: 2009 | H3: 2010 | I3: 2011 | J3: 2012 | K3: 2013 | L3: 2014 | M3: 2015 | N3: 2016 | O3: 2017 | P3: 2018 | Q3: 2019 | R3: 2020 | S3: 2021 | T3: 2022 | U3: 2023 | V3: 2024 | W3: 2025 | X3: 2026 | Y3: 2027
B5: Market size estimate (patients) | D5: Total prostate cancer 2012 | G5: Defined market mCRPC
D6: Incidence | E6: Deaths | F6: Growth | I6: Assume | AA6: Epidemiology
B7: Prostate cancer to mCRPC | C7: US | D7: 233159 | E7: 30383 | F7: 0 | G7: % deaths | H7: Global | I7: 1 | J7: =$I$7 -> 1 | K7: =$I$7 -> 1 | L7: =$I$7 -> 1 | M7: =$I$7 -> 1 | N7: =$I$7 -> 1 | O7: =$I$7 -> 1 | P7: =$I$7 -> 1 | Q7: =$I$7 -> 1 | ... Y7: =$I$7 -> 1 | AA7: http://globocan.iarc.fr/old/FactSheets/cancers/prostate-new.asp
C8: EU | D8: 345195 | E8: 71789 | F8: 0 | G8: % incidence | H8: Global | I8: 0.015 | J8: 0 | K8: =J8+$I$8 -> 0.015 | L8: =K8+$I$8 -> 0.03 | M8: =L8+$I$8 -> 0.045 | N8: =M8+$I$8 -> 0.06 | O8: =N8+$I$8 -> 0.075 | P8: =O8+$I$8 -> 0.09 | Q8: =P8+$I$8 -> 0.105 | R8: =Q8+$I$8 -> 0.12 | ... Y8: =X8+$I$8 -> 0.225
C9: Total US and EU | D9: =D7+D8 -> 578354 | E9: =E7+E8 -> 102172
B11: Defined market mCRPC | C11: US | I11: US | J11: =$E$7*J7+$D$7*J8 -> 30383 | K11: =$E$7*K7+$D$7*K8 -> 33880.385 | L11: =$E$7*L7+$D$7*L8 -> 37377.77 | M11: =$E$7*M7+$D$7*M8 -> 40875.155 | N11: =$E$7*N7+$D$7*N8 -> 44372.54 | O11: =$E$7*O7+$D$7*O8 -> 47869.925 | P11: =$E$7*P7+$D$7*P8 -> 51367.31 | Q11: =$E$7*Q7+$D$7*Q8 -> 54864.695 | ... Y11: =$E$7*Y7+$D$7*Y8 -> 82843.775
C12: Non-US (EU + Australia, Canada) | E12: AU + CA = | F12: =AD45 -> 0.13971779 | I12: Non-US | J12: =($E$8*J7+$D$8*J8)*(1+$F$12) -> 81819.2 | K12: =($E$8*K7+$D$8*K8)*(1+$F$12) -> 87720.574 | L12: =($E$8*L7+$D$8*L8)*(1+$F$12) -> 93621.947 | M12: =($E$8*M7+$D$8*M8)*(1+$F$12) -> 99523.32 | N12: =($E$8*N7+$D$8*N8)*(1+$F$12) -> 105424.69 | O12: =($E$8*O7+$D$8*O8)*(1+$F$12) -> 111326.07 | P12: =($E$8*P7+$D$8*P8)*(1+$F$12) -> 117227.44 | Q12: =($E$8*Q7+$D$8*Q8)*(1+$F$12) -> 123128.81 | ... Y12: =($E$8*Y7+$D$8*Y8)*(1+$F$12) -> 170339.8
C13: Total US and Non-US | I13: Total | J13: =J11+J12 -> 112202.2 | K13: =K11+K12 -> 121600.96 | L13: =L11+L12 -> 130999.72 | M13: =M11+M12 -> 140398.48 | N13: =N11+N12 -> 149797.23 | O13: =O11+O12 -> 159195.99 | P13: =P11+P12 -> 168594.75 | Q13: =Q11+Q12 -> 177993.51 | ... Y13: =Y11+Y12 -> 253183.57
I14: % growth | K14: =K13/J13-1 -> 0.083766256 | L14: =L13/K13-1 -> 0.07729181 | M14: =M13/L13-1 -> 0.071746401 | N14: =N13/M13-1 -> 0.06694345 | O14: =O13/N13-1 -> 0.062743203 | P14: =P13/O13-1 -> 0.059038913 | Q14: =Q13/P13-1 -> 0.055747633 | R14: =R13/Q13-1 -> 0.052803938 | ... Y14: =Y13/X13-1 -> 0.038553501
B16: Market share | I16: US | J16: 0.27260196 | K16: 0.46058016 | L16: 0.57685741 | M16: 0.65913145 | N16: 0.68953284 | O16: 0.7 | P16: 0.71 | Q16: 0.72 | R16: 0.73 | S16: 0.74 | T16: 0.74 | U16: 0.74 | V16: 0.74 | W16: 0.74 | X16: 0.74 | Y16: 0.74
B17: Androgen synthesis inhibitors | I17: Non-US | J17: 0.1521271 | K17: 0.28365836 | L17: 0.42960892 | M17: 0.46278679 | N17: 0.52470259 | O17: 0.57 | P17: 0.61 | Q17: 0.64 | R17: 0.66 | S17: 0.67 | T17: 0.67 | U17: 0.67 | V17: 0.67 | W17: 0.67 | X17: 0.67 | Y17: 0.67
I18: Total | J18: =J22/J13 -> 0.18475024 | K18: =K22/K13 -> 0.33295221 | L18: =L22/L13 -> 0.4716229 | M18: =M22/M13 -> 0.51994993 | N18: =N22/N13 -> 0.57352817 | O18: =O22/O13 -> 0.60909075 | P18: =P22/P13 -> 0.64046792 | Q18: =Q22/Q13 -> 0.66465919 | ... Y18: =Y22/Y13 -> 0.69290458
B20: Patients treated with androgen synthesis inhibitors | I20: US | J20: =J16*J11 -> 8282.4652 | K20: =K16*K11 -> 15604.633 | L20: =L16*L11 -> 21561.643 | M20: =M16*M11 -> 26942.1 | N20: =N16*N11 -> 30596.323 | O20: =O16*O11 -> 33508.948 | P20: =P16*P11 -> 36470.79 | Q20: =Q16*Q11 -> 39502.58 | ... Y20: =Y16*Y11 -> 61304.394
B21: Assumes 12 mth treatment | I21: Non-US | J21: =J17*J12 -> 12446.918 | K21: =K17*K12 -> 24882.674 | L21: =L17*L12 -> 40220.823 | M21: =M17*M12 -> 46058.078 | N21: =N17*N12 -> 55316.61 | O21: =O17*O12 -> 63455.858 | P21: =P17*P12 -> 71508.738 | Q21: =Q17*Q12 -> 78802.44 | ... Y21: =Y17*Y12 -> 114127.67
I22: Total | J22: =J20+J21 -> 20729.383 | K22: =K20+K21 -> 40487.307 | L22: =L20+L21 -> 61782.466 | M22: =M20+M21 -> 73000.178 | N22: =N20+N21 -> 85912.933 | O22: =O20+O21 -> 96964.805 | P22: =P20+P21 -> 107979.53 | Q22: =Q20+Q21 -> 118305.02 | ... Y22: =Y20+Y21 -> 175432.06
I23: % growth | K23: =K22/J22-1 -> 0.95313614 | L23: =L22/K22-1 -> 0.52597123 | M23: =M22/L22-1 -> 0.18156788 | N23: =N22/M22-1 -> 0.17688663 | O23: =O22/N22-1 -> 0.12864038 | P23: =P22/O22-1 -> 0.11359506 | Q23: =Q22/P22-1 -> 0.095624537 | R23: =R22/Q22-1 -> 0.079956206 | ... Y23: =Y22/X22-1 -> 0.038735166
B24: Prolutamide | D24: Competing products | E24: TTP advantage | F24: Target price | G24: Share of Voice
B25: Market share | C25: US | D25: =Control!I5 -> 2 | E25: =Control!I6 -> 1 | F25: =Control!I7 -> 0 | G25: =IF(U49=1, 1)+IF(Control!I16>0,1,0) -> 2 | I25: US | J25: =$N$25*J54 -> 0.067979287 | K25: =$N$25*K54 -> 0.19806557 | L25: =$N$25*L54 -> 0.24832843 | M25: =$N$25*M54 -> 0.33641287 | N25: =G27-0.0018 -> 0.38153333 | O25: =N25+O56 -> 0.42153333 | P25: =O25+P56 -> 0.46153333 | Q25: =P25+Q56 -> 0.48153333 | R25: =Q25+R56 -> 0.50153333 | S25: =R25+S56 -> 0.50153333 | T25: =S25+T56 -> 0.50153333 | U25: =T25+U56 -> 0.49653333 | V25: =U25+V56 -> 0.48653333 | ... Y25: =X25+Y56 -> 0.45653333
C26: Non-US | E26: =E25 -> 1 | F26: =Control!I8 -> 0 | G26: =U50 -> 1 | I26: Non-US | J26: =$N$25*J55 -> 0 | K26: =$N$25*K55 -> 0.047297521 | L26: =$N$25*L55 -> 0.19864959 | M26: =$N$25*M55 -> 0.34054215 | N26: =G28 -> 0.40333333 | O26: =N26+O57 -> 0.44333333 | P26: =O26+P57 -> 0.46333333 | Q26: =P26+Q57 -> 0.48333333 | R26: =Q26+R57 -> 0.50333333 | S26: =R26+S57 -> 0.50333333 | T26: =S26+T57 -> 0.50333333 | U26: =T26+U57 -> 0.49833333 | V26: =U26+V57 -> 0.48833333 | ... Y26: =X26+Y57 -> 0.068333333
B27: Adjusted market share | C27: US | D27: =IF(D25=2,E49,H49) -> 0.33333333 | E27: =IF(E25=1,D27+K49,D27) -> 0.38333333 | F27: =IF(F25=0,Q49,IF(F25=-30%,S49,IF(F25=30%,R49))) -> 0.38333333 | G27: =IF(G25<1,F27*(1+V49),F27) -> 0.38333333 | I27: Total | J27: =J31/J22 -> 0.027161256 | K27: =K31/K22 -> 0.1054066 | L27: =L31/L22 -> 0.21598715 | M27: =M31/M22 -> 0.33901816 | N27: =N31/N22 -> 0.39556966 | O27: =O31/O22 -> 0.43579972 | P27: =P31/P22 -> 0.46272537 | Q27: =Q31/Q22 -> 0.48273231 | ... Y27: =Y31/Y22 -> 0.20398907 | AA27: Pricing | AC27: Price/cap $ | AD27: Popn m | AE27: Pr x pop
C28: Non-US | D28: =D27 -> 0.33333333 | E28: =IF(E26=1,D28+K50,D28) -> 0.40333333 | F28: =IF(F26=0,Q50,IF(F26=-30%,S50,IF(F26=30%,R50))) -> 0.40333333 | G28: =IF(G26=1,F28,F28*(1+V50)) -> 0.40333333 | AA28: 1 | AB28: Australia | AC28: 23.46 | AD28: 24.2 | AE28: =AC28*AD28 -> 567.732
B29: Patients | I29: US | J29: =J25*J20 -> 563.03608 | K29: =K25*K20 -> 3090.7405 | L29: =L25*L20 -> 5354.3692 | M29: =M25*M20 -> 9063.6693 | N29: =N25*N20 -> 11673.517 | O29: =O25*O20 -> 14125.138 | P29: =P25*P20 -> 16832.485 | Q29: =Q25*Q20 -> 19021.809 | ... Y29: =Y25*Y20 -> 27987.499 | AA29: 1 | AB29: Belgium | AC29: 31.48 | AD29: 11.2 | AE29: =AC29*AD29 -> 352.576
I30: Non-US | K30: =K26*K21 -> 1176.8888 | L30: =L26*L21 -> 7989.8499 | M30: =M26*M21 -> 15684.717 | N30: =N26*N21 -> 22311.033 | O30: =O26*O21 -> 28132.097 | P30: =P26*P21 -> 33132.382 | Q30: =Q26*Q21 -> 38087.846 | R30: =R26*R21 -> 42863.828 | ... Y30: =Y26*Y21 -> 7798.7238 | AA30: 1 | AB30: Canada | AC30: 30.12 | AD30: 36.2 | AE30: =AC30*AD30 -> 1090.344
I31: Total | J31: =J29+J30 -> 563.03608 | K31: =K29+K30 -> 4267.6293 | L31: =L29+L30 -> 13344.219 | M31: =M29+M30 -> 24748.386 | N31: =N29+N30 -> 33984.55 | O31: =O29+O30 -> 42257.235 | P31: =P29+P30 -> 49964.867 | Q31: =Q29+Q30 -> 57109.655 | ... Y31: =Y29+Y30 -> 35786.223 | AA31: 1 | AB31: France | AC31: 26.73 | AD31: 65.3 | AE31: =AC31*AD31 -> 1745.469
F32: Packaging | H32: Pack size | I32: % growth | K32: =K31/J31-1 -> 6.5796728 | L32: =L31/K31-1 -> 2.1268459 | M32: =M31/L31-1 -> 0.85461479 | N32: =N31/M31-1 -> 0.37320268 | O32: =O31/N31-1 -> 0.24342489 | P32: =P31/O31-1 -> 0.18239792 | Q32: =Q31/P31-1 -> 0.14299624 | R32: =R31/Q31-1 -> 0.12470148 | ... Y32: =Y31/X31-1 -> -0.54695915 | AA32: 1 | AB32: Germany | AC32: 36.93 | AD32: 82.5 | AE32: =AC32*AD32 -> 3046.725
C33: Dose / day (mg) | E33: 160 | F33: Bottle / blister | H33: 100 | AA33: 1 | AB33: Italy | AC33: 26.01 | AD33: 61.2 | AE33: =AC33*AD33 -> 1591.812
B34: Packs sold 000 | C34: Capsule size (mg) | E34: 40 | I34: US | J34: =$H$36*J29/1000 -> 8.2203267 | K34: =$H$36*K29/1000 -> 45.124811 | L34: =$H$36*L29/1000 -> 78.17379 | M34: =$H$36*M29/1000 -> 132.32957 | N34: =$H$36*N29/1000 -> 170.43335 | O34: =$H$36*O29/1000 -> 206.22702 | P34: =$H$36*P29/1000 -> 245.75429 | Q34: =$H$36*Q29/1000 -> 277.71841 | ... Y34: =$H$36*Y29/1000 -> 408.61749 | AA34: 1 | AB34: Holland | AC34: 31.48 | AD34: 16.9 | AE34: =AC34*AD34 -> 532.012
C35: Treatment days | E35: 365 | I35: Non-US | J35: =$H$36*J30/1000 -> 0 | K35: =$H$36*K30/1000 -> 17.182577 | L35: =$H$36*L30/1000 -> 116.65181 | M35: =$H$36*M30/1000 -> 228.99686 | N35: =$H$36*N30/1000 -> 325.74108 | O35: =$H$36*O30/1000 -> 410.72862 | P35: =$H$36*P30/1000 -> 483.73278 | Q35: =$H$36*Q30/1000 -> 556.08255 | ... Y35: =$H$36*Y30/1000 -> 113.86137 | AA35: 1 | AB35: Norway | AC35: 32.43 | AD35: 5.2 | AE35: =AC35*AD35 -> 168.636
C36: Caps/patient per year | E36: =E33/E34*E35 -> 1460 | F36: Packs/patient per year | H36: =E36/H33 -> 14.6 | I36: Total | J36: =J34+J35 -> 8.2203267 | K36: =K34+K35 -> 62.307387 | L36: =L34+L35 -> 194.8256 | M36: =M34+M35 -> 361.32644 | N36: =N34+N35 -> 496.17443 | O36: =O34+O35 -> 616.95564 | P36: =P34+P35 -> 729.48706 | Q36: =Q34+Q35 -> 833.80097 | ... Y36: =Y34+Y35 -> 522.47885 | AA36: 1 | AB36: Spain | AC36: 32.38 | AD36: 47.3 | AE36: =AC36*AD36 -> 1531.574
AA37: 1 | AB37: Sweden | AC37: 26.96 | AD37: 9.8 | AE37: =AC37*AD37 -> 264.208
B38: Sales forecast $m | D38: Target 2012 Wholesale price $ | G38: Prem/disc | H38: Fcast price | I38: US | J38: =J34*$H$40/1000 -> 71.165835 | K38: =K34*$H$40/1000 -> 390.65902 | L38: =L34*$H$40/1000 -> 676.77395 | M38: =M34*$H$40/1000 -> 1145.6168 | N38: =N34*$H$40/1000 -> 1475.4927 | O38: =O34*$H$40/1000 -> 1785.3692 | P38: =P34*$H$40/1000 -> 2127.5686 | Q38: =Q34*$H$40/1000 -> 2404.2916 | ... Y38: =Y34*$H$40/1000 -> 3537.5242 | AA38: 1 | AB38: Switzer | AC38: 35.46 | AD38: 8.3 | AE38: =AC38*AD38 -> 294.318
D39: Per cap | E39: Per pack 100 | F39: Treatment | G39: Pack 100 | H39: Pack 100 | I39: Non-US | J39: =J35*$H$41/1000 -> 0 | K39: =K35*$H$41/1000 -> 53.555488 | L39: =L35*$H$41/1000 -> 363.58601 | M39: =M35*$H$41/1000 -> 713.74853 | N39: =N35*$H$41/1000 -> 1015.2856 | O39: =O35*$H$41/1000 -> 1280.1789 | P39: =P35*$H$41/1000 -> 1507.7218 | Q39: =Q35*$H$41/1000 -> 1733.2251 | ... Y39: =Y35*$H$41/1000 -> 354.88863 | AA39: 1 | AB39: UK | AC39: 35.65 | AD39: 64.2 | AE39: =AC39*AD39 -> 2288.73
C40: US | D40: =AE49 -> 86.573 | E40: =AE49*$H$33 -> 8657.3 | F40: =D40*E36 -> 126396.58 | G40: =F25 -> 0 | H40: =E40*(1+G40) -> 8657.3 | I40: Total | J40: =J38+J39 -> 71.165835 | K40: =K38+K39 -> 444.21451 | L40: =L38+L39 -> 1040.36 | M40: =M38+M39 -> 1859.3653 | N40: =N38+N39 -> 2490.7782 | O40: =O38+O39 -> 3065.548 | P40: =P38+P39 -> 3635.2904 | Q40: =Q38+Q39 -> 4137.5167 | ... Y40: =Y38+Y39 -> 3892.4128 | AA40: =SUM(AA28:AA39) -> 12 | AB40: Total | AC40: =SUM(AC28:AC39) -> 369.09 | AD40: =SUM(AD28:AD39) -> 432.3 | AE40: =SUM(AE28:AE39) -> 13474.136
C41: Non-US | D41: =AE41 -> 31.168485 | E41: =AE50*$H$33 -> 3116.8485 | F41: =E36*D41 -> 45505.988 | G41: =F26 -> 0 | H41: =E41*(1+G41) -> 3116.8485 | I41: % growth | K41: =K40/J40-1 -> 5.2419631 | L41: =L40/K40-1 -> 1.3420216 | M41: =M40/L40-1 -> 0.78723269 | N41: =N40/M40-1 -> 0.33958518 | O41: =O40/N40-1 -> 0.23075912 | P41: =P40/O40-1 -> 0.18585333 | Q41: =Q40/P40-1 -> 0.13815302 | R41: =R40/Q40-1 -> 0.12418591 | ... Y41: =Y40/X40-1 -> -0.3300975 | AB41: Av pr | AC41: =AC40/AA40 -> 30.7575 | AD41: Wt av pr | AE41: =AE40/AD40 -> 31.168485
AA42: 1 | AB42: Japan | AC42: 26.37 | AD42: 126.6 | AE42: =AC42*AD42 -> 3338.442
C43: Average net selling price per patient treatment $000 | J43: =J40*1000/J31 -> 126.39658 | K43: =K40*1000/K31 -> 104.08929 | L43: =L40*1000/L31 -> 77.963346 | M43: =M40*1000/M31 -> 75.130771 | N43: =N40*1000/N31 -> 73.291488 | O43: =O40*1000/O31 -> 72.544927 | P43: =P40*1000/P31 -> 72.75693 | Q43: =Q40*1000/Q31 -> 72.448637 | ... Y43: =Y40*1000/Y31 -> 108.76847 | AA43: =AA42+AA40 -> 13 | AB43: Av pr | AC43: =(AC40+AC42)/AA43 -> 30.42 | AD43: Wt av pr | AE43: =+(AE40+AE42)/(AD40+AD42) -> 30.081549
C44: Average net selling price per pack 100 caps $000 | J44: =J43/$H$36 -> 8.6573 | K44: =K43/$H$36 -> 7.1294036 | L44: =L43/$H$36 -> 5.3399552 | M44: =M43/$H$36 -> 5.1459432 | N44: =N43/$H$36 -> 5.0199649 | O44: =O43/$H$36 -> 4.9688306 | P44: =P43/$H$36 -> 4.9833514 | Q44: =Q43/$H$36 -> 4.9622354 | ... Y44: =Y43/$H$36 -> 7.4498954 | AB44: ANZ,CA | AD44: =AD28+AD30 -> 60.4
AC45: % popn | AD45: =AD44/AD40 -> 0.13971779
B46: Market share calculation | C46: Zipf's Law
C47: Entrants | D47: 2 | E47: MS% | F47: Entrants | G47: 3 | H47: MS% | J47: MS adjustment for TTP | M47: MS adjustment for price | P47: TTP MS | T47: MS adjustment for share of voice first 5 years from launch | AC47: 2012 Wholesale price / cap $
C48: 1 | D48: =1/C48 -> 1 | E48: =D48/$D$51 -> 0.66666667 | F48: 1 | G48: =1/F48 -> 1 | H48: =G48/$G$51 -> 0.54545455 | K48: % points | M48: = target | N48: > target | O48: < target | Q48: = target | R48: > target | S48: < target | T48: First 5 yrs | U48: 1 if > 100% | V48: < 100% | W48: > = 100% | AC48: Non Medic | AD48: Medicaid | AE48: Average
C49: 2 | D49: =1/C49 -> 0.5 | E49: =D49/$D$51 -> 0.33333333 | F49: 2 | G49: =1/F49 -> 0.5 | H49: =G49/$G$51 -> 0.27272727 | J49: US | K49: 0.05 | M49: 0 | N49: -0.05 | O49: =5% -> 0.05 | P49: =E27 -> 0.38333333 | Q49: =$P$49*(1+M49) -> 0.38333333 | R49: =$P$49*(1+N49) -> 0.36416667 | S49: =$P$49*(1+O49) -> 0.4025 | T49: =Control!I14 -> 1 | U49: =IF(T49<100%,0,1) -> 1 | V49: -0.25 | W49: 0 | Y49: =38/33 -> 1.1515152 | AC49: 88.48 | AD49: 69.41 | AE49: 86.573
F50: 3 | G50: =1/F50 -> 0.33333333 | H50: =G50/$G$51 -> 0.18181818 | J50: Non-US | K50: 0.07 | M50: 0 | N50: -0.25 | O50: =25% -> 0.25 | P50: =E28 -> 0.40333333 | Q50: =$P$50*(1++M50) -> 0.40333333 | R50: =$P$50*(1++N50) -> 0.3025 | S50: =$P$50*(1++O50) -> 0.50416667 | T50: =Control!I15 -> 1 | U50: =IF(T50<100%,0,1) -> 1 | V50: -0.25 | W50: 0 | Y50: =40/33 -> 1.2121212 | AE50: =AE41 -> 31.168485
D51: =SUM(D48:D50) -> 1.5 | E51: =SUM(E48:E50) -> 1 | G51: =SUM(G48:G50) -> 1.8333333 | H51: =SUM(H48:H50) -> 1 | AC51: Assumes 0% price growth
B53: Adoption curve | J53: 2012 | K53: 2013 | L53: 2014 | M53: 2015 | N53: 2016 | O53: 2017 | P53: 2018 | Q53: 2019 | R53: 2020 | S53: 2021 | T53: 2022 | U53: 2023 | V53: 2024 | W53: 2025 | X53: 2026 | Y53: 2027
I54: US | J54: 0.17817391 | K54: 0.51913043 | L54: 0.65086957 | M54: 0.88173913 | N54: 1 | O54: 0.04 | P54: 0.04 | Q54: 0.02 | R54: 0.02 | S54: 0 | T54: 0 | U54: -0.005 | V54: -0.01 | W54: -0.01 | X54: -0.01 | Y54: -0.01
I55: Non-US | J55: 0 | K55: 0.12396694 | L55: 0.52066116 | M55: 0.89256198 | N55: 1 | O55: 0.04 | P55: 0.02 | Q55: 0.02 | R55: 0.02 | S55: 0 | T55: 0 | U55: -0.005 | V55: -0.01 | W55: -0.01 | X55: -0.01 | Y55: -0.4
C56: Second 5 years promotion | E56: US | F56: =Control!J14 -> 1 | G56: =IF(F56<100%,50%,100%) -> 1 | H56: =IF(Control!I16>0,100%,G56) -> 1 | I56: US | O56: =$H$56*O54 -> 0.04 | P56: =$H$56*P54 -> 0.04 | Q56: =$H$56*Q54 -> 0.02 | R56: =$H$56*R54 -> 0.02 | S56: =$H$56*S54 -> 0 | T56: =$H$56*T54 -> 0 | U56: =$H$56*U54 -> -0.005 | V56: =$H$56*V54 -> -0.01 | ... Y56: =$H$56*Y54 -> -0.01
E57: Non-US | F57: =Control!J15 -> 1 | G57: =IF(F57<100%,50%,100%) -> 1 | H57: =G57 -> 1 | I57: Non-US | O57: =$H$57*O55 -> 0.04 | P57: =$H$57*P55 -> 0.02 | Q57: =$H$57*Q55 -> 0.02 | R57: =$H$57*R55 -> 0.02 | S57: =$H$57*S55 -> 0 | T57: =$H$57*T55 -> 0 | U57: =$H$57*U55 -> -0.005 | V57: =$H$57*V55 -> -0.01 | ... Y57: =$H$57*Y55 -> -0.4
B60: Cost of Goods data | J60: 2012 | K60: =J60+1 -> 2013 | L60: =K60+1 -> 2014 | M60: =L60+1 -> 2015 | N60: =M60+1 -> 2016 | O60: =N60+1 -> 2017 | P60: =O60+1 -> 2018 | Q60: =P60+1 -> 2019 | R60: =Q60+1 -> 2020 | ... Y60: =X60+1 -> 2027
B61: Volume of caps million | E61: =E36 -> 1460 | F61: Caps per patient per year | J61: =$E$61*J31/1000000 -> 0.82203267 | K61: =$E$61*K31/1000000 -> 6.2307387 | L61: =$E$61*L31/1000000 -> 19.48256 | M61: =$E$61*M31/1000000 -> 36.132644 | N61: =$E$61*N31/1000000 -> 49.617443 | O61: =$E$61*O31/1000000 -> 61.695564 | P61: =$E$61*P31/1000000 -> 72.948706 | Q61: =$E$61*Q31/1000000 -> 83.380097 | ... Y61: =$E$61*Y31/1000000 -> 52.247885
B62: Volume of kgs | E62: 40 | F62: mg per cap | J62: =$E$62*J61 -> 32.881307 | K62: =$E$62*K61 -> 249.22955 | L62: =$E$62*L61 -> 779.30239 | M62: =$E$62*M61 -> 1445.3057 | N62: =$E$62*N61 -> 1984.6977 | O62: =$E$62*O61 -> 2467.8225 | P62: =$E$62*P61 -> 2917.9483 | Q62: =$E$62*Q61 -> 3335.2039 | ... Y62: =$E$62*Y61 -> 2089.9154
B63: Volume of packs 000 | D63: Total | E63: 100 | F63: Caps per pack | J63: =J61*1000/$E$63 -> 8.2203267 | K63: =K61*1000/$E$63 -> 62.307387 | L63: =L61*1000/$E$63 -> 194.8256 | M63: =M61*1000/$E$63 -> 361.32644 | N63: =N61*1000/$E$63 -> 496.17443 | O63: =O61*1000/$E$63 -> 616.95564 | P63: =P61*1000/$E$63 -> 729.48706 | Q63: =Q61*1000/$E$63 -> 833.80097 | ... Y63: =Y61*1000/$E$63 -> 522.47885
B66: Price per pack average $ | K66: =K28/K63*1000 -> 0 | L66: =L28/L63*1000 -> 0 | M66: =M28/M63*1000 -> 0 | N66: =N28/N63*1000 -> 0 | O66: =O28/O63*1000 -> 0 | P66: =P28/P63*1000 -> 0 | Q66: =Q28/Q63*1000 -> 0 | R66: =R28/R63*1000 -> 0 | ... Y66: =Y28/Y63*1000 -> 0
B67: Batches per year | E67: Batch size packs | G67: =COG!G12 -> 5625 | H67: Number of batches | J67: =J63*1000/$G$67 -> 1.4613914 | K67: =K63*1000/$G$67 -> 11.076869 | L67: =L63*1000/$G$67 -> 34.635662 | M67: =M63*1000/$G$67 -> 64.235811 | N67: =N63*1000/$G$67 -> 88.208787 | O67: =O63*1000/$G$67 -> 109.681 | P67: =P63*1000/$G$67 -> 129.68659 | Q67: =Q63*1000/$G$67 -> 148.23128 | ... Y67: =Y63*1000/$G$67 -> 92.88513
B68: Batches per year | E68: Batch size packs | G68: =COG!K12 -> 11250 | H68: Number of batches | J68: =J63*1000/$G$68 -> 0.73069571 | K68: =K63*1000/$G$68 -> 5.5384344 | L68: =L63*1000/$G$68 -> 17.317831 | M68: =M63*1000/$G$68 -> 32.117905 | N68: =N63*1000/$G$68 -> 44.104394 | O68: =O63*1000/$G$68 -> 54.840501 | P68: =P63*1000/$G$68 -> 64.843295 | Q68: =Q63*1000/$G$68 -> 74.115642 | ... Y68: =Y63*1000/$G$68 -> 46.442565
C69: Switch batch size at batches pa | D69: 24 | E69: Batch size to be used | J69: =IF(J68>=$D$69,$G$68,$G$67) -> 5625 | K69: =IF(K68>=$D$69,$G$68,$G$67) -> 5625 | L69: =IF(L68>=$D$69,$G$68,$G$67) -> 5625 | M69: =IF(M68>=$D$69,$G$68,$G$67) -> 11250 | N69: =IF(N68>=$D$69,$G$68,$G$67) -> 11250 | O69: =IF(O68>=$D$69,$G$68,$G$67) -> 11250 | P69: =IF(P68>=$D$69,$G$68,$G$67) -> 11250 | Q69: =IF(Q68>=$D$69,$G$68,$G$67) -> 11250 | ... Y69: =IF(Y68>=$D$69,$G$68,$G$67) -> 11250
E70: Cumulative sales volume | H70: Batches | I70: =SUM(J70:Y70) -> 23.586961 | J70: =IF(J69=$G$67,J68,0) -> 0.73069571 | K70: =IF(K69=$G$67,K68,0) -> 5.5384344 | L70: =IF(L69=$G$67,L68,0) -> 17.317831 | M70: =IF(M69=$G$67,M68,0) -> 0 | N70: =IF(N69=$G$67,N68,0) -> 0 | O70: =IF(O69=$G$67,O68,0) -> 0 | P70: =IF(P69=$G$67,P68,0) -> 0 | Q70: =IF(Q69=$G$67,Q68,0) -> 0 | ... Y70: =IF(Y69=$G$67,Y68,0) -> 0
E71: Cumulative sales volume | H71: Batches | I71: =SUM(J71:Y71) -> 979.97892 | J71: =J68-J70 -> 0 | K71: =K68-K70 -> 0 | L71: =L68-L70 -> 0 | M71: =M68-M70 -> 32.117905 | N71: =N68-N70 -> 44.104394 | O71: =O68-O70 -> 54.840501 | P71: =P68-P70 -> 64.843295 | Q71: =Q68-Q70 -> 74.115642 | ... Y71: =Y68-Y70 -> 46.442565
B73: Sales with US co-commercialisation or 100% promotion by Atlas | J73: 2012 | K73: =J73+1 -> 2013 | L73: =K73+1 -> 2014 | M73: =L73+1 -> 2015 | N73: =M73+1 -> 2016 | O73: =N73+1 -> 2017 | P73: =O73+1 -> 2018 | Q73: =P73+1 -> 2019 | R73: =Q73+1 -> 2020 | ... Y73: =X73+1 -> 2027
B74: Patients treated with androgen synthesis inhibitors | J74: =J20 -> 8282.4652 | K74: =K20 -> 15604.633 | L74: =L20 -> 21561.643 | M74: =M20 -> 26942.1 | N74: =N20 -> 30596.323 | O74: =O20 -> 33508.948 | P74: =P20 -> 36470.79 | Q74: =Q20 -> 39502.58 | ... Y74: =Y20 -> 61304.394
B75: Market share | J75: 0.067979287 | K75: 0.19806557 | L75: 0.24832843 | M75: 0.33641287 | N75: 0.38153333 | O75: 0.42153333 | P75: 0.46153333 | Q75: 0.48153333 | R75: 0.50153333 | S75: 0.50153333 | T75: 0.50153333 | U75: 0.49653333 | V75: 0.48653333 | W75: 0.47653333 | X75: 0.46653333 | Y75: 0.45653333
B76: Number of patients prolutamide | J76: =J74*J75 -> 563.03608 | K76: =K74*K75 -> 3090.7405 | L76: =L74*L75 -> 5354.3692 | M76: =M74*M75 -> 9063.6693 | N76: =N74*N75 -> 11673.517 | O76: =O74*O75 -> 14125.138 | P76: =P74*P75 -> 16832.485 | Q76: =Q74*Q75 -> 19021.809 | ... Y76: =Y74*Y75 -> 27987.499
B77: Volume packs 000 | C77: Packs per patient | D77: =$H$36 -> 14.6 | J77: =J76*$D$77/1000 -> 8.2203267 | K77: =K76*$D$77/1000 -> 45.124811 | L77: =L76*$D$77/1000 -> 78.17379 | M77: =M76*$D$77/1000 -> 132.32957 | N77: =N76*$D$77/1000 -> 170.43335 | O77: =O76*$D$77/1000 -> 206.22702 | P77: =P76*$D$77/1000 -> 245.75429 | Q77: =Q76*$D$77/1000 -> 277.71841 | ... Y77: =Y76*$D$77/1000 -> 408.61749
B78: Sales $m | C78: Price per pack $ | D78: =$H$40 -> 8657.3 | J78: =J77*$D$78/1000 -> 71.165835 | K78: =K77*$D$78/1000 -> 390.65902 | L78: =L77*$D$78/1000 -> 676.77395 | M78: =M77*$D$78/1000 -> 1145.6168 | N78: =N77*$D$78/1000 -> 1475.4927 | O78: =O77*$D$78/1000 -> 1785.3692 | P78: =P77*$D$78/1000 -> 2127.5686 | Q78: =Q77*$D$78/1000 -> 2404.2916 | ... Y78: =Y77*$D$78/1000 -> 3537.5242
B79: Cost of goods per pack $ | J79: =COG!I57 -> 400.26389 | K79: =COG!J57 -> 400.26389 | L79: =COG!K57 -> 400.26389 | M79: =COG!L57 -> 272.48611 | N79: =COG!M57 -> 272.48611 | O79: =COG!N57 -> 272.48611 | P79: =COG!O57 -> 272.48611 | Q79: =COG!P57 -> 272.48611 | ... S79: =COG!R57 -> 272.48611 | T79: =S79 -> 272.48611 | U79: =T79 -> 272.48611 | V79: =U79 -> 272.48611 | W79: =V79 -> 272.48611 | X79: =W79 -> 272.48611 | Y79: =X79 -> 272.48611
B80: Cost of goods | J80: =J77*J79/1000 -> 3.2903 | K80: =K77*K79/1000 -> 18.061832 | L80: =L77*L79/1000 -> 31.290145 | M80: =M77*M79/1000 -> 36.05797 | N80: =N77*N79/1000 -> 46.440721 | O80: =O77*O79/1000 -> 56.193999 | P80: =P77*P79/1000 -> 66.96463 | Q80: =Q77*Q79/1000 -> 75.674411 | ... Y80: =Y77*Y79/1000 -> 111.34259
B81: Distribution | D81: 0.03 | J81: =$D$81*J78 -> 2.134975 | K81: =$D$81*K78 -> 11.719771 | L81: =$D$81*L78 -> 20.303218 | M81: =$D$81*M78 -> 34.368504 | N81: =$D$81*N78 -> 44.26478 | O81: =$D$81*O78 -> 53.561075 | P81: =$D$81*P78 -> 63.827057 | Q81: =$D$81*Q78 -> 72.128749 | ... Y81: =$D$81*Y78 -> 106.12573
B82: Gross profit | J82: =J78-J80-J81 -> 65.74056 | K82: =K78-K80-K81 -> 360.87742 | L82: =L78-L80-L81 -> 625.18059 | M82: =M78-M80-M81 -> 1075.1903 | N82: =N78-N80-N81 -> 1384.7872 | O82: =O78-O80-O81 -> 1675.6141 | P82: =P78-P80-P81 -> 1996.7769 | Q82: =Q78-Q80-Q81 -> 2256.4885 | ... Y82: =Y78-Y80-Y81 -> 3320.0559
B84: Forecast US sales above | J84: =J38 -> 71.165835 | K84: =K38 -> 390.65902 | L84: =L38 -> 676.77395 | M84: =M38 -> 1145.6168 | N84: =N38 -> 1475.4927 | O84: =O38 -> 1785.3692 | P84: =P38 -> 2127.5686 | Q84: =Q38 -> 2404.2916 | ... Y84: =Y38 -> 3537.5242
B85: Better / worse than 100% | J85: =J38-J84 -> 0 | K85: =K38-K84 -> 0 | L85: =L38-L84 -> 0 | M85: =M38-M84 -> 0 | N85: =N38-N84 -> 0 | O85: =O38-O84 -> 0 | P85: =P38-P84 -> 0 | Q85: =Q38-Q84 -> 0 | ... Y85: =Y38-Y84 -> 0

Sheet COG
A1: COST OF GOODS | E1: Assumptions in red | G1: Assumptions in yellow box from control panel
C2: Flucitra 120mg capsule pilot scale cost | E2: Pilot scale cost of goods per capsule for clinical trial supplies | K2: =G23/30*L2 -> 1067.3704 | L2: 100 | M2: pilot scalefactor
A3: Licensee Buys Finished Packs from Licensor (at 2009 Costs) | N3: Licensee Manufactures and Packs Inhouse (at 2009 Costs)
B4: Assumptions | E4: Batch size kg | G4: 25 | I4: Batch size kg | K4: 50 | N4: Batch size kg | S4: =G4 -> 25 | U4: Batch size kg | W4: =K4 -> 50
E5: API cost per kg $ | G5: 15000 | I5: =E5 -> API cost per kg $ | K5: =G5 -> 15000 | Q5: =E5 -> API cost per kg $ | S5: =G5 -> 15000 | U5: =Q5 -> API cost per kg $ | W5: =G5 -> 15000
E6: API Cost / batch $ | G6: =G4*G5 -> 375000 | I6: =E6 -> API Cost / batch $ | K6: =K4*K5 -> 750000 | Q6: =E6 -> API Cost / batch $ | S6: =S4*S5 -> 375000 | U6: =Q6 -> API Cost / batch $ | W6: =W4*W5 -> 750000
E7: Yield | G7: 0.9 | I7: Yield | K7: =G7 -> 0.9 | Q7: Yield | S7: =G7 -> 0.9 | U7: =Q7 -> Yield | W7: =K7 -> 0.9
E8: Caps API mg | G8: =G4*G7*1000000 -> 22500000 | I8: =E8 -> Caps API mg | K8: =K4*K7*1000000 -> 45000000 | Q8: =E8 -> Caps API mg | S8: =S4*S7*1000000 -> 22500000 | U8: =Q8 -> Caps API mg | W8: =W4*W7*1000000 -> 45000000
E9: Mg per cap | G9: 40 | I9: =E9 -> Mg per cap | K9: =G9 -> 40 | Q9: =E9 -> Mg per cap | S9: =G9 -> 40 | U9: =Q9 -> Mg per cap | W9: =S9 -> 40
E10: Caps per batch | G10: =G8/G9 -> 562500 | I10: =E10 -> Caps per batch | K10: =K8/K9 -> 1125000 | Q10: =E10 -> Caps per batch | S10: =S8/S9 -> 562500 | U10: =Q10 -> Caps per batch | W10: =W8/W9 -> 1125000
C11: =100*2.18 -> 218 | E11: Pack size caps | G11: 100 | I11: =E11 -> Pack size caps | K11: =G11 -> 100 | Q11: =E11 -> Pack size caps | S11: =G11 -> 100 | U11: =Q11 -> Pack size caps | W11: =S11 -> 100
E12: Packs per batch | G12: =G10/G11 -> 5625 | I12: =E12 -> Packs per batch | K12: =K10/K11 -> 11250 | Q12: =E12 -> Packs per batch | S12: =S10/S11 -> 5625 | U12: =Q12 -> Packs per batch | W12: =W10/W11 -> 11250
B14: Variable costs | G14: Cost / pack $ | K14: Cost / pack $ | S14: =G14 -> Cost / pack $ | W14: =S14 -> Cost / pack $
C15: API | G15: =G6/G12 -> 66.666667 | K15: =K6/K12 -> 66.666667 | N15: API | S15: =S6/S12 -> 66.666667 | W15: =W6/W12 -> 66.666667
C16: Packing materials and excipients | G16: 17 | K16: =G16 -> 17 | N16: Packing materials and excipients | S16: =G16 -> 17 | W16: =S16 -> 17
C17: Direct labour | G17: 17 | K17: =G17 -> 17 | N17: Direct labour | S17: =G17 -> 17 | W17: =S17 -> 17
C18: Total variable costs | G18: =SUM(G15:G17) -> 100.66667 | K18: =SUM(K15:K17) -> 100.66667 | N18: Total variable costs | S18: =SUM(S15:S17) -> 100.66667 | W18: =SUM(W15:W17) -> 100.66667
B19: Fixed costs | N19: Fixed costs
C20: Fixed costs | F20: 1000 | G20: =F20/G12*1000 -> 177.77778 | J20: =F20 -> 1000 | K20: =J20/K12*1000 -> 88.888889 | O20: Fixed costs | R20: =F20 -> 1000 | S20: =R20/S12*1000 -> 177.77778 | V20: =R20 -> 1000 | W20: =V20/W12*1000 -> 88.888889
B21: Total variable and fixed costs | G21: =G20+G18 -> 278.44444 | K21: =K20+K18 -> 189.55556 | N21: Total variable and fixed costs | S21: =S18+S20 -> 278.44444 | W21: =W18+W20 -> 189.55556
C22: Shipping and insurance and CMO profit | E22: CMO profit | F22: 0.15 | G22: =F22*G21 -> 41.766667 | J22: =F22 -> 0.15 | K22: =J22*K21 -> 28.433333 | O22: Shipping and insurance | R22: 0.02 | S22: =R22*S21 -> 5.5688889 | V22: =R22 -> 0.02 | W22: =V22*W21 -> 3.7911111
B23: Total costs | G23: =G21+G22 -> 320.21111 | K23: =K21+K22 -> 217.98889 | N23: Total costs excluding depreciation | Q23: Capex $m | R23: Capacity m | S23: =S21+S22 -> 284.01333 | U23: Capex $m | V23: Capacity m | W23: =W21+W22 -> 193.34667
C24: Licensor mark-up | F24: =Control!I12 -> 0.25 | G24: =F24*G23 -> 80.052778 | J24: =Control!I12 -> 0.25 | K24: =J24*K23 -> 54.497222 | N24: Depreciation | Q24: 15 | R24: =Sales!I70 -> 23.586961 | S24: =Q24/R24 -> 0.63594458 | U24: 30 | V24: =Sales!I71 -> 979.97892 | W24: =U24/V24 -> 0.030612903
B25: Total supply price to licensee | G25: =G23+G24 -> 400.26389 | K25: =K23+K24 -> 272.48611 | N25: Total cost of goods | S25: =S23+S24 -> 284.64928 | W25: =W23+W24 -> 193.37728
C26: Average net selling price per pack 2016 | G26: =Sales!$N$44*1000 -> 5019.9649 | K26: =G26 -> 5019.9649 | O26: Net selling price | S26: =G26 -> 5019.9649 | W26: =K26 -> 5019.9649
C27: COG % net selling price | G27: =G25/G26 -> 0.079734399 | K27: =K25/K26 -> 0.054280481 | O27: COG % net selling price | S27: =S25/S26 -> 0.056703439 | W27: =W25/W26 -> 0.038521639
C28: Assumes annual cost increases affecting direct and indirect costs are offset by savings from improvement in productivity
A30: Cost/benefit Licensee inhouse manufacture | E30: =Control!Y2 -> 2008 | F30: =E30+1 -> 2009 | G30: =F30+1 -> 2010 | H30: =G30+1 -> 2011 | I30: =H30+1 -> 2012 | J30: =I30+1 -> 2013 | K30: =J30+1 -> 2014 | L30: =K30+1 -> 2015 | M30: =L30+1 -> 2016 | ... R30: =Q30+1 -> 2021
C31: Volume of packs 000 | I31: =Sales!J63 -> 8.2203267 | J31: =Sales!K63 -> 62.307387 | K31: =Sales!L63 -> 194.8256 | L31: =Sales!M63 -> 361.32644 | M31: =Sales!N63 -> 496.17443 | N31: =Sales!O63 -> 616.95564 | O31: =Sales!P63 -> 729.48706 | P31: =Sales!Q63 -> 833.80097 | ... R31: =Sales!S63 -> 999.53953
B32: If Licensor supply
C33: Supply price per pack | D33: $ | I33: =IF(Sales!J70>0,COG!$G$25,COG!$K$25) -> 400.26389 | J33: =IF(Sales!K70>0,COG!$G$25,COG!$K$25) -> 400.26389 | K33: =IF(Sales!L70>0,COG!$G$25,COG!$K$25) -> 400.26389 | L33: =IF(Sales!M70>0,COG!$G$25,COG!$K$25) -> 272.48611 | M33: =IF(Sales!N70>0,COG!$G$25,COG!$K$25) -> 272.48611 | N33: =IF(Sales!O70>0,COG!$G$25,COG!$K$25) -> 272.48611 | O33: =IF(Sales!P70>0,COG!$G$25,COG!$K$25) -> 272.48611 | P33: =IF(Sales!Q70>0,COG!$G$25,COG!$K$25) -> 272.48611 | ... R33: =IF(Sales!S70>0,COG!$G$25,COG!$K$25) -> 272.48611
C34: Cost of goods | D34: $m | I34: =I31*I33/1000 -> 3.2903 | J34: =J31*J33/1000 -> 24.939397 | K34: =K31*K33/1000 -> 77.981651 | L34: =L31*L33/1000 -> 98.456435 | M34: =M31*M33/1000 -> 135.20064 | N34: =N31*N33/1000 -> 168.11184 | O34: =O31*O33/1000 -> 198.77509 | P34: =P31*P33/1000 -> 227.19918 | ... R34: =R31*R33/1000 -> 272.36064
B35: If Licensee inhouse manufacture
C36: If investment of $15m
C37: Cost per pack | D37: $ | I37: =$S$25 -> 284.64928 | J37: =$S$25 -> 284.64928 | K37: =$S$25 -> 284.64928 | L37: =$S$25 -> 284.64928 | M37: =$S$25 -> 284.64928 | N37: =$S$25 -> 284.64928 | O37: =$S$25 -> 284.64928 | P37: =$S$25 -> 284.64928 | ... R37: =$S$25 -> 284.64928
C38: Cost of goods | D38: $m | H38: =H37*H31 -> 0 | I38: =I37*I31/1000 -> 2.3399101 | J38: =J37*J31/1000 -> 17.735753 | K38: =K37*K31/1000 -> 55.456966 | L38: =L37*L31/1000 -> 102.85131 | M38: =M37*M31/1000 -> 141.23569 | N38: =N37*N31/1000 -> 175.61598 | O38: =O37*O31/1000 -> 207.64797 | P38: =P37*P31/1000 -> 237.34084 | ... R38: =R37*R31/1000 -> 284.5182
C39: Saving or (loss) from inhouse manufacture | D39: $m | H39: =H34-H38 -> 0 | I39: =I34-I38 -> 0.95038988 | J39: =J34-J38 -> 7.2036444 | K39: =K34-K38 -> 22.524686 | L39: =L34-L38 -> -4.3948737 | M39: =M34-M38 -> -6.0350523 | N39: =N34-N38 -> -7.5041343 | O39: =O34-O38 -> -8.8728728 | ... R39: =R34-R38 -> -12.157566
C40: Capital expenditure if inhouse manufacture | D40: $m | G40: =-Q24 -> -15
C41: Cash flow | E41: =E39+E40 -> 0 | F41: =F39+F40 -> 0 | G41: =G39+G40 -> -15 | H41: =H39+H40 -> 0 | I41: =I39+I40 -> 0.95038988 | J41: =J39+J40 -> 7.2036444 | K41: =K39+K40 -> 22.524686 | L41: =L39+L40 -> -4.3948737 | ... R41: =R39+R40 -> -12.157566
C42: NPV | D42: =Control!G45 -> 0.12 | E42: NPV | F42: =NPV(D42,H41:R41)+G41 -> -18.154237 | G42: IRR | H42: =IRR(G41:R41) -> #NUM!
C43: If investment of $30m
C44: Cost per pack | D44: $ | I44: =$W$25 -> 193.37728 | J44: =$W$25 -> 193.37728 | K44: =$W$25 -> 193.37728 | L44: =$W$25 -> 193.37728 | M44: =$W$25 -> 193.37728 | N44: =$W$25 -> 193.37728 | O44: =$W$25 -> 193.37728 | P44: =$W$25 -> 193.37728 | ... R44: =$W$25 -> 193.37728
C45: Cost of goods | D45: $m | H45: =H44*H31/1000 -> 0 | I45: =I44*I31/1000 -> 1.5896244 | J45: =J44*J31/1000 -> 12.048833 | K45: =K44*K31/1000 -> 37.674844 | L45: =L44*L31/1000 -> 69.872323 | M45: =M44*M31/1000 -> 95.948861 | N45: =N44*N31/1000 -> 119.3052 | O45: =O44*O31/1000 -> 141.06622 | ... R45: =R44*R31/1000 -> 193.28823
C46: Saving or (loss) from inhouse manufacture | D46: $m | H46: =H34-H45 -> 0 | I46: =I34-I45 -> 1.7006755 | J46: =J34-J45 -> 12.890564 | K46: =K34-K45 -> 40.306807 | L46: =L34-L45 -> 28.584112 | M46: =M34-M45 -> 39.251779 | N46: =N34-N45 -> 48.806639 | O46: =O34-O45 -> 57.708869 | ... R46: =R34-R45 -> 79.072404
C47: Capital expenditure if inhouse manufacture | D47: $m | G47: =-U24 -> -30
C48: Cash flow | E48: =E46+E47 -> 0 | F48: =F46+F47 -> 0 | G48: =G46+G47 -> -30 | H48: =H46+H47 -> 0 | I48: =I46+I47 -> 1.7006755 | J48: =J46+J47 -> 12.890564 | K48: =K46+K47 -> 40.306807 | L48: =L46+L47 -> 28.584112 | ... R48: =R46+R47 -> 79.072404
C49: NPV | D49: =Control!G45 -> 0.12 | E49: NPV | F49: =NPV(D49,H48:R48)+G48 -> 158.04126 | G49: IRR | H49: =IRR(G48:O48) -> 0.44429913
A51: Cost of goods used in Project P&L
B52: Will the Licensee manufacture inhouse? | F52: =Control!I10 -> 0 | G52: Enter 1 for YES or 0 for NO
B53: If answer is yes will the capital expenditure be $15m or $30m? | F53: =Control!I11 -> 30 | G53: Enter 15 for $15m or 30 for $30m | K53: =F52*F53 -> 0
C54: Volume of packs 000 | D54: US | I54: =Sales!J34 -> 8.2203267 | J54: =Sales!K34 -> 45.124811 | K54: =Sales!L34 -> 78.17379 | L54: =Sales!M34 -> 132.32957 | M54: =Sales!N34 -> 170.43335 | N54: =Sales!O34 -> 206.22702 | O54: =Sales!P34 -> 245.75429 | P54: =Sales!Q34 -> 277.71841 | ... R54: =Sales!S34 -> 335.1896
C55: Volume of packs 000 | D55: Non US | I55: =Sales!J35 -> 0 | J55: =Sales!K35 -> 17.182577 | K55: =Sales!L35 -> 116.65181 | L55: =Sales!M35 -> 228.99686 | M55: =Sales!N35 -> 325.74108 | N55: =Sales!O35 -> 410.72862 | O55: =Sales!P35 -> 483.73278 | P55: =Sales!Q35 -> 556.08255 | ... R55: =Sales!S35 -> 664.34993
D56: Total | I56: =I54+I55 -> 8.2203267 | J56: =J54+J55 -> 62.307387 | K56: =K54+K55 -> 194.8256 | L56: =L54+L55 -> 361.32644 | M56: =M54+M55 -> 496.17443 | N56: =N54+N55 -> 616.95564 | O56: =O54+O55 -> 729.48706 | P56: =P54+P55 -> 833.80097 | ... R56: =R54+R55 -> 999.53953
C57: Cost of goods per pack | I57: =I59/I56*1000 -> 400.26389 | J57: =J59/J56*1000 -> 400.26389 | K57: =K59/K56*1000 -> 400.26389 | L57: =L59/L56*1000 -> 272.48611 | M57: =M59/M56*1000 -> 272.48611 | N57: =N59/N56*1000 -> 272.48611 | O57: =O59/O56*1000 -> 272.48611 | P57: =P59/P56*1000 -> 272.48611 | ... R57: =R59/R56*1000 -> 272.48611
C59: Cost of goods $m | I59: =IF($K$53=0,I34,IF($K$53=15,I38,IF($K$53=30,I45))) -> 3.2903 | J59: =IF($K$53=0,J34,IF($K$53=15,J38,IF($K$53=30,J45))) -> 24.939397 | K59: =IF($K$53=0,K34,IF($K$53=15,K38,IF($K$53=30,K45))) -> 77.981651 | L59: =IF($K$53=0,L34,IF($K$53=15,L38,IF($K$53=30,L45))) -> 98.456435 | M59: =IF($K$53=0,M34,IF($K$53=15,M38,IF($K$53=30,M45))) -> 135.20064 | N59: =IF($K$53=0,N34,IF($K$53=15,N38,IF($K$53=30,N45))) -> 168.11184 | O59: =IF($K$53=0,O34,IF($K$53=15,O38,IF($K$53=30,O45))) -> 198.77509 | P59: =IF($K$53=0,P34,IF($K$53=15,P38,IF($K$53=30,P45))) -> 227.19918 | ... R59: =IF($K$53=0,R34,IF($K$53=15,R38,IF($K$53=30,R45))) -> 272.36064
D60: US | I60: =I57*I54/1000 -> 3.2903 | J60: =J57*J54/1000 -> 18.061832 | K60: =K57*K54/1000 -> 31.290145 | L60: =L57*L54/1000 -> 36.05797 | M60: =M57*M54/1000 -> 46.440721 | N60: =N57*N54/1000 -> 56.193999 | O60: =O57*O54/1000 -> 66.96463 | P60: =P57*P54/1000 -> 75.674411 | ... R60: =R57*R54/1000 -> 91.334511
D61: Non US | I61: =I57*I55/1000 -> 0 | J61: =J57*J55/1000 -> 6.8775649 | K61: =K57*K55/1000 -> 46.691506 | L61: =L57*L55/1000 -> 62.398465 | M61: =M57*M55/1000 -> 88.759919 | N61: =N57*N55/1000 -> 111.91784 | O61: =O57*O55/1000 -> 131.81046 | P61: =P57*P55/1000 -> 151.52477 | ... R61: =R57*R55/1000 -> 181.02613
C63: Capital expenditure $m | G63: =IF(AND($K$53>0),$F$53,0) -> 0
C64: Licensor supply profit $m | D64: =IF(F52>0,0,F24) -> 0.25 | E64: =$D$64*E59 -> 0 | F64: =$D$64*F59 -> 0 | G64: =$D$64*G59 -> 0 | H64: =$D$64*H59 -> 0 | I64: =$D$64*I59 -> 0.82257499 | J64: =J59-J59/(1+$D$64) -> 4.9878794 | K64: =K59-K59/(1+$D$64) -> 15.59633 | L64: =L59-L59/(1+$D$64) -> 19.691287 | M64: =M59-M59/(1+$D$64) -> 27.040128 | N64: =N59-N59/(1+$D$64) -> 33.622368 | O64: =O59-O59/(1+$D$64) -> 39.755019 | P64: =P59-P59/(1+$D$64) -> 45.439837 | Q64: =Q59-Q59/(1+$D$64) -> 51.106251 | R64: =R59-R59/(1+$D$64) -> 54.472128
C65: Licensor supply profit NPV $m | D65: =Control!G45 -> 0.12 | E65: NPV | F65: =NPV(D65,F64:R64)+E64 -> 94.671787
A67: Check | C67: Sales | I67: =Sales!J40 -> 71.165835 | J67: =Sales!K40 -> 444.21451 | K67: =Sales!L40 -> 1040.36 | L67: =Sales!M40 -> 1859.3653 | M67: =Sales!N40 -> 2490.7782 | N67: =Sales!O40 -> 3065.548 | O67: =Sales!P40 -> 3635.2904 | P67: =Sales!Q40 -> 4137.5167 | ... R67: =Sales!S40 -> 4972.515
C68: COG % | I68: =I59/I67 -> 0.046234263 | J68: =J59/J67 -> 0.056142689 | K68: =K59/K67 -> 0.074956414 | L68: =L59/L67 -> 0.052951636 | M68: =M59/M67 -> 0.054280481 | N68: =N59/N67 -> 0.054839082 | O68: =O59/O67 -> 0.054679289 | P68: =P59/P67 -> 0.054911968 | ... R68: =R59/R67 -> 0.054773216
C70: COG savings NPV to control page | J70: =IF(K53=0,0,IF(K53=15,F42,IF(K53=30,F49))) -> 0

Sheet R&D
A1: DEVELOPMENT AND REGULATORY
C2: Assumptions in yellow box from control panel | F2: Are additional patients needed for the biclautamide studies? | G2: =Control!V10 -> 0 | H2: 1 = YES | L2: 1 | M2: =L2+1 -> 2 | N2: =M2+1 -> 3 | O2: =N2+1 -> 4 | P2: =O2+1 -> 5 | Q2: =P2+1 -> 6 | R2: =Q2+1 -> 7 | S2: =R2+1 -> 8 | T2: =S2+1 -> 9 | U2: =T2+1 -> 10 | V2: Total
E3: 2005 | F3: 2006 | G3: 2007 | H3: 2008 | I3: 2009 | J3: 2010 | K3: 2011 | L3: 2012 | M3: 2013 | N3: 2014 | O3: 2015 | P3: 2016 | Q3: 2017 | R3: 2018 | S3: 2019 | T3: 2020 | U3: 2021 | V3: 2009-21
C4: Synthesise, test and identify lead compound from 170 compounds | E4: 0.087 | F4: 1.007 | V4: =SUM(I4:U4) -> 0
C5: Manufacture lead compound for IND enabling preclinical and early clinical studies and scale up | E5: 0.087 | F5: 1.007 | G5: 1 | H5: 2.2 | I5: 4.9 | J5: 5.4 | K5: 6.7 | L5: 7 | M5: 7.5 | N5: 8 | O5: 8.5 | V5: =SUM(I5:U5) -> 48
C6: Complete IND enabling preclinical studies and file IND | E6: 0.087 | F6: 1.007 | G6: 0.5 | V6: =SUM(I6:U6) -> 0
C7: Total non-clinical | E7: =SUM(E4:E6) -> 0.261 | F7: =SUM(F4:F6) -> 3.021 | G7: =SUM(G4:G6) -> 1.5 | H7: =SUM(H4:H6) -> 2.2 | I7: =SUM(I4:I6) -> 4.9 | J7: =SUM(J4:J6) -> 5.4 | K7: =SUM(K4:K6) -> 6.7 | L7: =SUM(L4:L6) -> 7 | ... U7: =SUM(U4:U6) -> 0 | V7: =SUM(I7:U7) -> 48
C8: Prostate cancer clinical studies
C9: Combined Phase 1 / 2a clinical study | G9: =T51 -> 1.10211 | V9: =SUM(I9:U9) -> 0
C10: Extension | H10: =T52 -> 6.6948 | V10: =SUM(I10:U10) -> 0
C11: AFFIRM: Phase 3 DB extended to open label | I11: =$T$53*U53 -> 14.024655 | J11: =$T$53*V53 -> 27.411826 | K11: =$T$53*W53 -> 22.311951 | L11: =K11 -> 22.311951 | M11: =L11 -> 22.311951 | N11: =M11 -> 22.311951 | O11: =N11 -> 22.311951 | P11: =O11 -> 22.311951 | V11: =SUM(I11:U11) -> 175.30819
C12: PREVAIL: Phase 3 DB extended to open label | J12: =$T$54*V54 -> 23.72894 | K12: =$T$54*W54 -> 52.203668 | L12: =$T$54*X54 -> 18.983152 | M12: =L12 -> 18.983152 | N12: =M12 -> 18.983152 | O12: 10 | V12: =SUM(I12:U12) -> 142.88206
C13: TERRAIN: Phase 2 DB extended to open label | K13: =$T$55*W55 -> 5.08125 | L13: =$T$55*X55 -> 5.08125 | M13: =$T$55*Y55 -> 10.1625 | N13: =M13 -> 10.1625 | O13: =N13 -> 10.1625 | P13: =O13 -> 10.1625 | V13: =SUM(I13:U13) -> 50.8125
C14: STRIVE: Phase 2 DB, | L14: =$T$56*X56 -> 10.997712 | M14: =$T$56*Y56 -> 10.997712 | V14: =SUM(I14:U14) -> 21.995424
C15: PLATO: Phase 4 | L15: =$T$57*X57 -> 26.91592 | M15: =$T$57*Y57 -> 18.841144 | N15: =$T$57*Z57 -> 8.074776 | O15: =N15 -> 8.074776 | P15: =O15 -> 8.074776 | V15: =SUM(I15:U15) -> 69.981392
C16: PROSPER: Phase 3 DB | L16: =$T$58*X58 -> 13.04784 | M16: =$T$58*Y58 -> 21.7464 | N16: =$T$58*Z58 -> 21.7464 | O16: =$T$58*AA58 -> 30.44496 | V16: =SUM(I16:U16) -> 86.9856
C17: EMBARK: Phase 3 | N17: =$T$59*Z59 -> 41.48544 | O17: =$T$59*AA59 -> 36.29976 | P17: =$T$59*AB59 -> 25.9284 | V17: =SUM(I17:U17) -> 103.7136
C18: M1 HSPC | P18: =$T$60*AB60 -> 15.334 | Q18: =$T$60*AC60 -> 30.668 | R18: =$T$60*AD60 -> 15.334 | V18: =SUM(I18:U18) -> 61.336
C19: Other Prolutamide prostate cancer studies | L19: 2.7 | M19: 0.9 | N19: 2.2 | O19: 4.3 | Q19: 20 | R19: =Q19 -> 20 | S19: =R19 -> 20 | T19: =S19 -> 20 | U19: =T19 -> 20 | V19: =SUM(I19:U19) -> 110.1
C20: Total prostate cancer phase 3 | G20: =SUM(G9:G19)-G15 -> 1.10211 | H20: =SUM(H9:H19)-H15 -> 6.6948 | I20: =SUM(I9:I19)-I15 -> 14.024655 | J20: =SUM(J9:J19)-J15 -> 51.140766 | K20: =SUM(K9:K19)-K15 -> 79.596869 | L20: =SUM(L9:L19)-L15 -> 73.121905 | M20: =SUM(M9:M19)-M15 -> 85.101715 | N20: =SUM(N9:N19)-N15 -> 116.88944 | ... U20: =SUM(U9:U19)-U15 -> 20 | V20: =SUM(I20:U20) -> 753.13338
C21: Total prostate cancer Phase 4 | G21: =G15 -> 0 | H21: =H15 -> 0 | I21: =I15 -> 0 | J21: =J15 -> 0 | K21: =K15 -> 0 | L21: =L15 -> 26.91592 | M21: =M15 -> 18.841144 | N21: =N15 -> 8.074776 | ... U21: =U15 -> 0 | V21: =SUM(I21:U21) -> 69.981392
C22: Breast cancer | V22: =SUM(I22:U22) -> 0
C23: AR+ TNBC Phase 2 open label | L23: =$T$62*X62 -> 3.06328 | M23: =$T$62*Y62 -> 3.06328 | V23: =SUM(I23:U23) -> 6.12656
C24: AR+ or PgR+ and HER normal Phase 2 DB, combo exemestane | M24: 3.20606 | N24: 6.41212 | O24: 3.20606 | V24: =SUM(I24:U24) -> 12.82424
C25: AR+ HER2 Amplfied Phase 2, Xtandi added to trastuzumab | N25: =$T$64*Z64 -> 1.0576 | O25: =$T$64*AA64 -> 2.1152 | P25: =$T$64*AB64 -> 1.0576 | V25: =SUM(I25:U25) -> 4.2304
C26: Liver cancer | V26: =SUM(I26:U26) -> 0
C27: Phase 2 | P27: =$T$66*AB66 -> 1.85184 | Q27: =$T$66*AC66 -> 3.70368 | R27: =$T$66*AD66 -> 1.85184 | V27: =SUM(I27:U27) -> 7.40736
C28: Total non prostate cancer studies | E28: =SUM(E23:E27) -> 0 | F28: =SUM(F23:F27) -> 0 | G28: =SUM(G23:G27) -> 0 | H28: =SUM(H23:H27) -> 0 | I28: =SUM(I23:I27) -> 0 | J28: =SUM(J23:J27) -> 0 | K28: =SUM(K23:K27) -> 0 | L28: =SUM(L23:L27) -> 3.06328 | ... U28: =SUM(U23:U27) -> 0 | V28: =SUM(I28:U28) -> 30.58856
C29: Total clinical costs | E29: =E20+E21+E28 -> 0 | F29: =F20+F21+F28 -> 0 | G29: =G20+G21+G28 -> 1.10211 | H29: =H20+H21+H28 -> 6.6948 | I29: =I20+I21+I28 -> 14.024655 | J29: =J20+J21+J28 -> 51.140766 | K29: =K20+K21+K28 -> 79.596869 | L29: =L20+L21+L28 -> 103.10111 | ... U29: =U20+U21+U28 -> 20 | V29: =SUM(I29:U29) -> 853.70333
C30: Total R&D | E30: =E29+E7 -> 0.261 | F30: =F29+F7 -> 3.021 | G30: =G29+G7 -> 2.60211 | H30: =H29+H7 -> 8.8948 | I30: =I29+I7 -> 18.924655 | J30: =J29+J7 -> 56.540766 | K30: =K29+K7 -> 86.296869 | L30: =L29+L7 -> 110.10111 | ... U30: =U29+U7 -> 20 | V30: =SUM(I30:U30) -> 901.70333
E31: 0.261 | F31: 3.021 | G31: 2.60211 | H31: 8.8948 | I31: 18.924655 | J31: 56.540766 | K31: 86.296869 | L31: 110.10111 | M31: 117.7122 | N31: 140.43394 | O31: 135.41521 | P31: 84.721067 | Q31: 34.37168 | R31: 17.18584 | S31: 0 | T31: 0 | U31: 0
A32: R&D Costs Paid by Licensee/Lor | E32: % Lee pays? | V32: Total
C33: Manufacture lead compound for IND enabling preclinical and early clinical studies and scale up | E33: =Control!F22 -> 0.5 | I33: =$E$33*I7 -> 2.45 | J33: =$E$33*J7 -> 2.7 | K33: =$E$33*K7 -> 3.35 | L33: =$E$33*L7 -> 3.5 | M33: =$E$33*M7 -> 3.75 | N33: =$E$33*N7 -> 4 | O33: =$E$33*O7 -> 4.25 | P33: =$E$33*P7 -> 0 | ... U33: =$E$33*U7 -> 0 | V33: =SUM(I33:U33) -> 24
C34: Total prostate cancer phase 3 | E34: =Control!F23 -> 1 | I34: =$E$34*I20 -> 14.024655 | J34: =$E$34*J20 -> 51.140766 | K34: =$E$34*K20 -> 79.596869 | L34: =$E$34*L20 -> 73.121905 | M34: =$E$34*M20 -> 85.101715 | N34: =$E$34*N20 -> 116.88944 | O34: =$E$34*O20 -> 113.51917 | P34: =$E$34*P20 -> 73.736851 | ... U34: =$E$34*U20 -> 20 | V34: =SUM(I34:U34) -> 753.13338
C35: Total prostate cancer Phase 4 | E35: =Control!F24 -> 1 | I35: =$E$35*I21 -> 0 | J35: =$E$35*J21 -> 0 | K35: =$E$35*K21 -> 0 | L35: =$E$35*L21 -> 26.91592 | M35: =$E$35*M21 -> 18.841144 | N35: =$E$35*N21 -> 8.074776 | O35: =$E$35*O21 -> 8.074776 | P35: =$E$35*P21 -> 8.074776 | ... U35: =$E$35*U21 -> 0 | V35: =SUM(I35:U35) -> 69.981392
C36: Total non prostate cancer studies | E36: =Control!F25 -> 0.5 | I36: =$E$36*I28 -> 0 | J36: =$E$36*J28 -> 0 | K36: =$E$36*K28 -> 0 | L36: =$E$36*L28 -> 1.53164 | M36: =$E$36*M28 -> 3.13467 | N36: =$E$36*N28 -> 3.73486 | O36: =$E$36*O28 -> 2.66063 | P36: =$E$36*P28 -> 1.45472 | ... U36: =$E$36*U28 -> 0 | V36: =SUM(I36:U36) -> 15.29428
B37: Licensee costs (to Lee vs Lor sheet) | E37: =SUM(G37:U37) -> 862.40905 | F37: =SUM(F33:F36) -> 0 | G37: =SUM(G33:G36) -> 0 | H37: =SUM(H33:H36) -> 0 | I37: =SUM(I33:I36) -> 16.474655 | J37: =SUM(J33:J36) -> 53.840766 | K37: =SUM(K33:K36) -> 82.946869 | L37: =SUM(L33:L36) -> 105.06947 | M37: =SUM(M33:M36) -> 110.82753 | ... U37: =SUM(U33:U36) -> 20 | V37: =SUM(I37:U37) -> 862.40905
B38: Licensor costs (to Lee vs Lor sheet) | E38: =SUM(G38:U38) -> 39.29428 | I38: =I30-I37 -> 2.45 | J38: =J30-J37 -> 2.7 | K38: =K30-K37 -> 3.35 | L38: =L30-L37 -> 5.03164 | M38: =M30-M37 -> 6.88467 | N38: =N30-N37 -> 7.73486 | O38: =O30-O37 -> 6.91063 | P38: =P30-P37 -> 1.45472 | ... U38: =U30-U37 -> 0 | V38: =SUM(I38:U38) -> 39.29428
A40: R&D Costs used in Project P&L | I40: Phase 3 | J40: Phase 3 | K40: Regulatory | L40: Launch
B41: Project | I41: =I3 -> 2009 | J41: =J3 -> 2010 | K41: =K3 -> 2011 | L41: =L3 -> 2012 | M41: =M3 -> 2013 | N41: =N3 -> 2014 | O41: =O3 -> 2015 | P41: =P3 -> 2016 | ... U41: =U3 -> 2021 | V41: Total
C42: Total non-clinical | I42: =I7 -> 4.9 | J42: =J7 -> 5.4 | K42: =K7 -> 6.7 | L42: =L7 -> 7 | M42: =M7 -> 7.5 | N42: =N7 -> 8 | O42: =O7 -> 8.5 | P42: =P7 -> 0 | ... U42: =U7 -> 0 | V42: =SUM(I42:U42) -> 48
C43: Total prostate cancer phase 3 | I43: =I20 -> 14.024655 | J43: =J20 -> 51.140766 | K43: =K20 -> 79.596869 | L43: =L20 -> 73.121905 | M43: =M20 -> 85.101715 | N43: =N20 -> 116.88944 | O43: =O20 -> 113.51917 | P43: =P20 -> 73.736851 | ... U43: =U20 -> 20 | V43: =SUM(I43:U43) -> 753.13338
C44: Total prostate cancer Phase 4 | I44: =I21 -> 0 | J44: =J21 -> 0 | K44: =K21 -> 0 | L44: =L21 -> 26.91592 | M44: =M21 -> 18.841144 | N44: =N21 -> 8.074776 | O44: =O21 -> 8.074776 | P44: =P21 -> 8.074776 | ... U44: =U21 -> 0 | V44: =SUM(I44:U44) -> 69.981392
C45: Total non prostate cancer studies | I45: =I28 -> 0 | J45: =J28 -> 0 | K45: =K28 -> 0 | L45: =L28 -> 3.06328 | M45: =M28 -> 6.26934 | N45: =N28 -> 7.46972 | O45: =O28 -> 5.32126 | P45: =P28 -> 2.90944 | ... U45: =U28 -> 0 | V45: =SUM(I45:U45) -> 30.58856
B46: Total development & reg costs $m | I46: =SUM(I42:I45) -> 18.924655 | J46: =SUM(J42:J45) -> 56.540766 | K46: =SUM(K42:K45) -> 86.296869 | L46: =SUM(L42:L45) -> 110.10111 | M46: =SUM(M42:M45) -> 117.7122 | N46: =SUM(N42:N45) -> 140.43394 | O46: =SUM(O42:O45) -> 135.41521 | P46: =SUM(P42:P45) -> 84.721067 | ... U46: =SUM(U42:U45) -> 20 | V46: =SUM(I46:U46) -> 901.70333
A48: Assumptions
C49: Prolutamide clinical | D49: Indication | E49: Comparator | F49: End point | G49: Dose | H49: Patients | I49: Average | J49: Start | K49: Enrolled | L49: FSR | M49: $k/patient | N49: CRO | O49: Mg | P49: Days | Q49: kgs | R49: Price/kg | S49: CTS | T49: Total | U49: 2009 | V49: 2010 | W49: 2011 | X49: 2012 | Y49: 2013 | Z49: 2014 | AA49: 2015 | AB49: 2016 | AC49: =AB49+1 -> 2017 | AD49: =AC49+1 -> 2018 | AE49: =AD49+1 -> 2019 | AF49: =AE49+1 -> 2020 | AG49: =AF49+1 -> 2021
C50: Prostate cancer | E50: 7 dose groups | I50: Months | J50: 1st patnt | N50: $m | S50: $m | T50: $m
C51: Combined Phase 1 / 2a clinical study | D51: US | E51: 30, 90, 160, 250, 350, 450, 600 | G51: 30-600mg/day | H51: 21 | I51: 3 | J51: 39234 | K51: 39783 | M51: 50 | N51: =H51*M51/1000 -> 1.05 | O51: =(30+90+160+250+350+450+600)*3 -> 5790 | P51: =I51*30 -> 90 | Q51: =O51*P51/1000000 -> 0.5211 | R51: 100000 | S51: =Q51*R51/1000000 -> 0.05211 | T51: =S51+N51 -> 1.10211
C52: Extension | D52: US | E52: 30, 90, 160, 250, 350, 450, 600 | G52: 30-600mg/day | H52: 120 | I52: 3 | J52: 39356 | L52: 39965 | M52: 50 | N52: =H52*M52/1000 -> 6 | O52: =(30+90+160+250+350+450+600)*40 -> 77200 | P52: =I52*30 -> 90 | Q52: =O52*P52/1000000 -> 6.948 | R52: 100000 | S52: =Q52*R52/1000000 -> 0.6948 | T52: =S52+N52 -> 6.6948
C53: AFFIRM: Phase 3 DB extended to open label | D53: mCRPC in docetaxel pre treated patients | E53: placebo | F53: Overall S | G53: 160mg once daily | H53: 1199 | I53: 6.6 | J53: 40057 | L53: 40848 | M53: 50 | N53: =H53*M53/1000 -> 59.95 | O53: =H53*160 -> 191840 | P53: =I53*30 -> 198 | Q53: =O53*P53/1000000 -> 37.98432 | R53: 100000 | S53: =Q53*R53/1000000 -> 3.798432 | T53: =S53+N53 -> 63.748432 | U53: 0.22 | V53: 0.43 | W53: 0.35
C54: PREVAIL: Phase 3 DB extended to open label | D54: mCRPC in pre chemo patients | E54: placebo | F54: PFS | G54: 160mg once daily | H54: 1717 | I54: 11 | J54: 40422 | L54: 41548 | M54: 50 | N54: =H54*M54/1000 -> 85.85 | O54: =H54*160 -> 274720 | P54: =I54*30 -> 330 | Q54: =O54*P54/1000000 -> 90.6576 | R54: 100000 | S54: =Q54*R54/1000000 -> 9.06576 | T54: =S54+N54 -> 94.91576 | V54: 0.25 | W54: 0.55 | X54: 0.2 | Y54: 0
C55: TERRAIN: Phase 2 DB extended to open label | D55: mCRPC in pre chemo patients | E55: bicalutamide | F55: PFS | G55: 160mg once daily | H55: =IF($G$2=1,2*375,375) -> 375 | I55: =17.5/2 -> 8.75 | J55: 40603 | K55: 41456 | L55: 42005 | M55: 50 | N55: =H55*M55/1000 -> 18.75 | O55: =H55*160 -> 60000 | P55: =I55*30 -> 262.5 | Q55: =O55*P55/1000000 -> 15.75 | R55: 100000 | S55: =Q55*R55/1000000 -> 1.575 | T55: =S55+N55 -> 20.325 | W55: 0.25 | X55: 0.25 | Y55: 0.5 | Z55: 0
C56: STRIVE: Phase 2 DB, | D56: CRPC in pre chemo patients | E56: bicalutamide | F56: PFS | G56: 160mg once daily | H56: =IF($G$2=1,2*396,396) -> 396 | I56: =23.1/2 -> 11.55 | J56: 41122 | K56: 41699 | L56: 42095 | M56: 50 | N56: =H56*M56/1000 -> 19.8 | O56: =H56*160 -> 63360 | P56: =I56*30 -> 346.5 | Q56: =O56*P56/1000000 -> 21.95424 | R56: 100000 | S56: =Q56*R56/1000000 -> 2.195424 | T56: =S56+N56 -> 21.995424 | X56: 0.5 | Y56: 0.5 | Z56: 0
C57: PLATO: Phase 4 | D57: mCRPC in pre chemo patients | E57: abiraterone | F57: PFS | G57: 160mg once daily | H57: 509 | I57: 12 | J57: 41579 | K57: 41883 | M57: 100 | N57: =H57*M57/1000 -> 50.9 | O57: =H57*160 -> 81440 | P57: =I57*30 -> 360 | Q57: =O57*P57/1000000 -> 29.3184 | R57: 100000 | S57: =Q57*R57/1000000 -> 2.93184 | T57: =S57+N57 -> 53.83184 | X57: 0.5 | Y57: 0.35 | Z57: 0.15
C58: PROSPER: Phase 3 DB | D58: non-m CRPC | E58: placebo | F58: MFS | G58: 160mg once daily | H58: 1560 | I58: 12 | J58: 41609 | M58: 50 | N58: =H58*M58/1000 -> 78 | O58: =H58*160 -> 249600 | P58: =I58*30 -> 360 | Q58: =O58*P58/1000000 -> 89.856 | R58: 100000 | S58: =Q58*R58/1000000 -> 8.9856 | T58: =S58+N58 -> 86.9856 | X58: 0.15 | Y58: 0.25 | Z58: 0.25 | AA58: 0.35 | AB58: 0
C59: EMBARK: Phase 3 | D59: non-m CRPC | F59: MFS | G59: 160mg once daily | H59: 1860 | I59: 12 | J59: 42005 | M59: 50 | N59: =H59*M59/1000 -> 93 | O59: =H59*160 -> 297600 | P59: =I59*30 -> 360 | Q59: =O59*P59/1000000 -> 107.136 | R59: 100000 | S59: =Q59*R59/1000000 -> 10.7136 | T59: =S59+N59 -> 103.7136 | Z59: 0.4 | AA59: 0.35 | AB59: 0.25 | AC59: 0
C60: M1 HSPC | F60: Overall S | G60: 160mg once daily | H60: 1100 | I60: 12 | J60: 42370 | M60: 50 | N60: =H60*M60/1000 -> 55 | O60: =H60*160 -> 176000 | P60: =I60*30 -> 360 | Q60: =O60*P60/1000000 -> 63.36 | R60: 100000 | S60: =Q60*R60/1000000 -> 6.336 | T60: =S60+N60 -> 61.336 | AB60: 0.25 | AC60: 0.5 | AD60: 0.25
C61: Breast cancer
C62: AR+ TNBC Phase 2 open label | D62: Advanced TNBC | F62: CBR16 | G62: 160mg once daily | H62: 118 | I62: 4 | J62: 41000 | K62: 41974 | M62: 50 | N62: =H62*M62/1000 -> 5.9 | O62: =H62*160 -> 18880 | P62: =I62*30 -> 120 | Q62: =O62*P62/1000000 -> 2.2656 | R62: 100000 | S62: =Q62*R62/1000000 -> 0.22656 | T62: =S62+N62 -> 6.12656 | X62: 0.5 | Y62: 0.5
C63: AR+ or PgR+ and HER normal Phase 2 DB, combo exemestane | D63: Advanced breast cancer | E63: plbo + exemastane | F63: CBR24 | G63: 160mg once daily | H63: 247 | I63: 4 | J63: 41609 | K63: 42064 | L63: 42644 | M63: 50 | N63: =H63*M63/1000 -> 12.35 | O63: =H63*160 -> 39520 | P63: =I63*30 -> 120 | Q63: =O63*P63/1000000 -> 4.7424 | R63: 100000 | S63: =Q63*R63/1000000 -> 0.47424 | T63: =S63+N63 -> 12.82424 | Y63: 0.25 | Z63: 0.5 | AA63: 0.25
C64: AR+ HER2 Amplfied Phase 2, prolutamide added to trastuzumab | D64: Advanced breast cancer | F64: CBR24 | G64: 160mg once daily | H64: 80 | I64: 6 | J64: 41852 | M64: 50 | N64: =H64*M64/1000 -> 4 | O64: =H64*160 -> 12800 | P64: =I64*30 -> 180 | Q64: =O64*P64/1000000 -> 2.304 | R64: 100000 | S64: =Q64*R64/1000000 -> 0.2304 | T64: =S64+N64 -> 4.2304 | Z64: 0.25 | AA64: 0.5 | AB64: 0.25
C65: Liver cancer
C66: Phase 2 | D66: Advanced liver cancer | F66: Overall S | G66: 160mg once daily | H66: 144 | I66: 3 | J66: 42370 | M66: 50 | N66: =H66*M66/1000 -> 7.2 | O66: =H66*160 -> 23040 | P66: =I66*30 -> 90 | Q66: =O66*P66/1000000 -> 2.0736 | R66: 100000 | S66: =Q66*R66/1000000 -> 0.20736 | T66: =S66+N66 -> 7.40736 | AB66: 0.25 | AC66: 0.5 | AD66: 0.25

Sheet S&M
A1: SALES AND MARKETING | D1: Assumptions in red | F1: =Control!Y2 -> 2008 | G1: Assumptions in yellow box from control panel
B3: Hospital and KOL Salesmen | D3: US | E3: Non US | F3: Total | H3: Payers | K3: US | L3: Non US | M3: Total
C4: Target audience urologist / oncologist | D4: 10000 | E4: 20000 | F4: =D4+E4 -> 30000 | H4: Total payer accounts | K4: 5000 | L4: 10000 | M4: =K4+L4 -> 15000
C5: Target calls per doctor per annum | D5: 12 | E5: 12 | H5: Accounts per executive | K5: 25 | L5: 25
C6: Target calls per annum | D6: =D4*D5 -> 120000 | E6: =E4*E5 -> 240000 | F6: =D6+E6 -> 360000 | H6: Number of major account managers | K6: =K4/K5 -> 200 | L6: =L4/L5 -> 400
C7: Working days per salesman | D7: 200 | E7: 200 | H7: Cost per manager $000 | J7: 0.25 | K7: =D11*(1+$J$7) -> 250 | L7: =E11*(1+$J$7) -> 187.5
C8: Calls per day per salesman | D8: 3 | E8: 3 | H8: Total costs $m | K8: =K6*K7/1000 -> 50 | L8: =L6*L7/1000 -> 75 | M8: =K8+L8 -> 125
C9: Annual calls per salesman | D9: =D7*D8 -> 600 | E9: =E7*E8 -> 600 | H9: Apportionment
C10: Number of salesmen | D10: =D6/D9 -> 200 | E10: =E6/E9 -> 400 | H10: % time dealing with prolutamide | K10: 0.5 | L10: 0.75 | M10: =M11/M8 -> 0.65
C11: Cost per salesman $000 | D11: 200 | E11: 150 | H11: Apportioned cost | K11: =K8*K10 -> 25 | L11: =L8*L10 -> 56.25 | M11: =K11+L11 -> 81.25
C12: Total employment costs $m | D12: =D10*D11/1000 -> 40 | E12: =E10*E11/1000 -> 60 | F12: =D12+E12 -> 100
C13: Cost per call $ | D13: =D12/D6*1000000 -> 333.33333 | E13: =E12/E6*1000000 -> 250 | F13: =F12/F6*1000000 -> 277.77778 | H13: Marketing Executives | K13: US | L13: Non US | M13: Total
B14: Salesforce Meetings | D14: US | E14: Non US | F14: Total | H14: Headcount | K14: 50 | L14: 100 | M14: =K14+L14 -> 150
C15: Target audience | D15: =D4 -> 10000 | E15: =E4 -> 20000 | F15: =F4 -> 30000 | H15: Cost per head $000 | K15: 300 | L15: 200
C16: Physicians per meeting | D16: 6 | E16: 6 | H16: Total employment costs $m | K16: =K14*K15/1000 -> 15 | L16: =L14*L15/1000 -> 20 | M16: =K16+L16 -> 35
C17: Meetings per annum | D17: =D15/D16 -> 1666.6667 | E17: =E15/E16 -> 3333.3333 | H17: Marketing
C18: Cost per meeting $000 | D18: 2 | E18: 3 | H18: Advertising | K18: 2 | L18: 4
C19: Total costs $m | D19: =D17*D18/1000 -> 3.3333333 | E19: =E17*E18/1000 -> 10 | F19: =D19+E19 -> 13.333333 | H19: PR | K19: 4 | L19: 8
B20: Total hospital and KOL salesforce costs $m | D20: =D19+D12 -> 43.333333 | E20: =E19+E12 -> 70 | F20: =D20+E20 -> 113.33333 | H20: Total costs $m | K20: =K18+K19 -> 6 | L20: =L18+L19 -> 12 | M20: =K20+L20 -> 18
B21: Total S&M | D21: =D20+K11+K25 -> 109.33333 | E21: =E20+L11+L25 -> 178.25 | F21: =D21+E21 -> 287.58333 | H21: Symposia
H22: Number per year | K22: 4 | L22: 4
B23: Apportionment | E23: Full time on target product | F23: 1 | H23: Cost $m | K23: 5 | L23: 5
E24: First line detail 2 products | F24: 0.65 | H24: Total costs $m | K24: =K22*K23 -> 20 | L24: =L22*L23 -> 20 | M24: =K24+L24 -> 40
E25: Second line detail 2 products | F25: 0.35 | H25: Total marketing costs | K25: =K24+K20+K16 -> 41 | L25: =L24+L20+L16 -> 52 | M25: =M24+M20+M16 -> 93
A28: Sales and marketing costs | E28: =F1+1 -> 2009 | F28: =E28+1 -> 2010 | G28: =F28+1 -> 2011 | H28: =G28+1 -> 2012 | I28: =H28+1 -> 2013 | J28: =I28+1 -> 2014 | K28: =J28+1 -> 2015 | L28: =K28+1 -> 2016 | M28: =L28+1 -> 2017 | ... Q28: =P28+1 -> 2021
B29: US | H29: =Control!I14 -> 1 | I29: =H29 -> 1 | J29: =I29 -> 1 | K29: =J29 -> 1 | L29: =K29 -> 1 | M29: =Control!J14 -> 1 | N29: =M29 -> 1 | O29: =N29 -> 1 | P29: =O29 -> 1 | Q29: =P29 -> 1
C30: Apportioned salesforce cost $m | H30: =$D$20*H29 -> 43.333333 | I30: =$D$20*I29 -> 43.333333 | J30: =$D$20*J29 -> 43.333333 | K30: =$D$20*K29 -> 43.333333 | L30: =$D$20*L29 -> 43.333333 | M30: =$D$20*M29 -> 43.333333 | N30: =$D$20*N29 -> 43.333333 | O30: =$D$20*O29 -> 43.333333 | ... Q30: =$D$20*Q29 -> 43.333333
C31: Payer management | H31: =K11 -> 25 | I31: =H31 -> 25 | J31: =I31 -> 25 | K31: =J31 -> 25 | L31: =K31 -> 25 | M31: =L31 -> 25 | N31: =M31 -> 25 | O31: =N31 -> 25 | P31: =O31 -> 25 | Q31: =P31 -> 25
C32: Marketing cost $m | H32: =$K$25 -> 41 | I32: =$K$25 -> 41 | J32: =$K$25 -> 41 | K32: =$K$25 -> 41 | L32: =$K$25 -> 41 | M32: =$K$25 -> 41 | N32: =$K$25 -> 41 | O32: =$K$25 -> 41 | ... Q32: =$K$25 -> 41
B33: Sales and marketing costs $m | H33: =SUM(H30:H32) -> 109.33333 | I33: =SUM(I30:I32) -> 109.33333 | J33: =SUM(J30:J32) -> 109.33333 | K33: =SUM(K30:K32) -> 109.33333 | L33: =SUM(L30:L32) -> 109.33333 | M33: =SUM(M30:M32) -> 109.33333 | N33: =SUM(N30:N32) -> 109.33333 | O33: =SUM(O30:O32) -> 109.33333 | ... Q33: =SUM(Q30:Q32) -> 109.33333
B34: Sales and marketing costs $m including partner | H34: =H33 -> 109.33333 | I34: =I33 -> 109.33333 | J34: =J33 -> 109.33333 | K34: =K33 -> 109.33333 | L34: =L33 -> 109.33333 | M34: =M33 -> 109.33333 | N34: =N33 -> 109.33333 | O34: =O33 -> 109.33333 | ... Q34: =Q33 -> 109.33333
B35: Sales | H35: =Sales!J38 -> 71.165835 | I35: =Sales!K38 -> 390.65902 | J35: =Sales!L38 -> 676.77395 | K35: =Sales!M38 -> 1145.6168 | L35: =Sales!N38 -> 1475.4927 | M35: =Sales!O38 -> 1785.3692 | N35: =Sales!P38 -> 2127.5686 | O35: =Sales!Q38 -> 2404.2916 | ... Q35: =Sales!S38 -> 2901.8369
C36: % sales | H36: =H34/H35 -> 1.5363177 | I36: =I34/I35 -> 0.27986896 | J36: =J34/J35 -> 0.16155074 | K36: =K34/K35 -> 0.095436217 | L36: =L34/L35 -> 0.074099544 | M36: =M34/M35 -> 0.061238502 | N36: =N34/N35 -> 0.051388864 | O36: =O34/O35 -> 0.045474239 | ... Q36: =Q34/Q35 -> 0.037677284
B38: Non-US | I38: =Control!I15 -> 1 | J38: =I38 -> 1 | K38: =J38 -> 1 | L38: =K38 -> 1 | M38: =L38 -> 1 | N38: =Control!J15 -> 1 | O38: =N38 -> 1 | P38: =O38 -> 1 | Q38: =P38 -> 1
C39: Apportioned salesforce cost $m | I39: =$E$20*I38 -> 70 | J39: =$E$20*J38 -> 70 | K39: =$E$20*K38 -> 70 | L39: =$E$20*L38 -> 70 | M39: =$E$20*M38 -> 70 | N39: =$E$20*N38 -> 70 | O39: =$E$20*O38 -> 70 | P39: =$E$20*P38 -> 70 | Q39: =$E$20*Q38 -> 70
C40: Payer management | I40: =L11 -> 56.25 | J40: =I40 -> 56.25 | K40: =J40 -> 56.25 | L40: =K40 -> 56.25 | M40: =L40 -> 56.25 | N40: =M40 -> 56.25 | O40: =N40 -> 56.25 | P40: =O40 -> 56.25 | Q40: =P40 -> 56.25
C41: Marketing cost $m | I41: =$L$25 -> 52 | J41: =$L$25 -> 52 | K41: =$L$25 -> 52 | L41: =$L$25 -> 52 | M41: =$L$25 -> 52 | N41: =$L$25 -> 52 | O41: =$L$25 -> 52 | P41: =$L$25 -> 52 | Q41: =$L$25 -> 52
B42: Sales and marketing costs $m | H42: =SUM(H39:H41) -> 0 | I42: =SUM(I39:I41) -> 178.25 | J42: =SUM(J39:J41) -> 178.25 | K42: =SUM(K39:K41) -> 178.25 | L42: =SUM(L39:L41) -> 178.25 | M42: =SUM(M39:M41) -> 178.25 | N42: =SUM(N39:N41) -> 178.25 | O42: =SUM(O39:O41) -> 178.25 | ... Q42: =SUM(Q39:Q41) -> 178.25
B43: Sales | H43: =Sales!K134 -> 0 | I43: =Sales!K39 -> 53.555488 | J43: =Sales!L39 -> 363.58601 | K43: =Sales!M39 -> 713.74853 | L43: =Sales!N39 -> 1015.2856 | M43: =Sales!O39 -> 1280.1789 | N43: =Sales!P39 -> 1507.7218 | O43: =Sales!Q39 -> 1733.2251 | P43: =Sales!R39 -> 1950.5608 | Q43: =Sales!S39 -> 2070.6781
C44: % sales | I44: =I42/I43 -> 3.3283237 | J44: =J42/J43 -> 0.49025539 | K44: =K42/K43 -> 0.24973782 | L44: =L42/L43 -> 0.17556637 | M44: =M42/M43 -> 0.13923836 | N44: =N42/N43 -> 0.11822473 | O44: =O42/O43 -> 0.10284296 | P44: =P42/P43 -> 0.091383974 | Q44: =Q42/Q43 -> 0.086082913
B46: Total US and Non-US | H46: =H34+H42 -> 109.33333 | I46: =I34+I42 -> 287.58333 | J46: =J34+J42 -> 287.58333 | K46: =K34+K42 -> 287.58333 | L46: =L34+L42 -> 287.58333 | M46: =M34+M42 -> 287.58333 | N46: =N34+N42 -> 287.58333 | O46: =O34+O42 -> 287.58333 | ... Q46: =Q34+Q42 -> 287.58333
B47: Sales | H47: =H35+H43 -> 71.165835 | I47: =I35+I43 -> 444.21451 | J47: =J35+J43 -> 1040.36 | K47: =K35+K43 -> 1859.3653 | L47: =L35+L43 -> 2490.7782 | M47: =M35+M43 -> 3065.548 | N47: =N35+N43 -> 3635.2904 | O47: =O35+O43 -> 4137.5167 | ... Q47: =Q35+Q43 -> 4972.515
C48: % sales | H48: =H46/H47 -> 1.5363177 | I48: =I46/I47 -> 0.64739743 | J48: =J46/J47 -> 0.27642676 | K48: =K46/K47 -> 0.15466747 | L48: =L46/L47 -> 0.11545923 | M48: =M46/M47 -> 0.093811393 | N48: =N46/N47 -> 0.079108766 | O48: =O46/O47 -> 0.069506265 | ... Q48: =Q46/Q47 -> 0.057834583
A51: Sales and marketing costs phasing | G51: US | H51: 0.5 | I51: 1.3 | J51: 2.15 | K51: 2.4 | L51: 2.4 | M51: 2.4 | N51: 2.4 | O51: 2.4 | P51: 2.4 | Q51: 2.4
G52: Non US | I52: 0.25 | J52: 0.8 | K52: 1.45 | L52: 1.45 | M52: 1.4 | N52: 1.4 | O52: 1.4 | P52: 1.4 | Q52: 1.4
A54: S&M Costs used in Project P&L | E54: =F1+1 -> 2009 | F54: =E54+1 -> 2010 | G54: =F54+1 -> 2011 | H54: =G54+1 -> 2012 | I54: =H54+1 -> 2013 | J54: =I54+1 -> 2014 | K54: =J54+1 -> 2015 | L54: =K54+1 -> 2016 | M54: =L54+1 -> 2017 | ... Q54: =P54+1 -> 2021
B55: Total S&M costs included in project P&L | D55: US | H55: =H51*H34 -> 54.666667 | I55: =I51*I34 -> 142.13333 | J55: =J51*J34 -> 235.06667 | K55: =K51*K34 -> 262.4 | L55: =L51*L34 -> 262.4 | M55: =M51*M34 -> 262.4 | N55: =N51*N34 -> 262.4 | O55: =O51*O34 -> 262.4 | ... Q55: =Q51*Q34 -> 262.4
C56: Co commercialisation partner >0 = YES | D56: =Control!I16 -> 0.5 | H56: =IF($D$56>0,H81,0) -> 10 | I56: =IF($D$56>0,I81,0) -> 26 | J56: =IF($D$56>0,J81,0) -> 43 | K56: =IF($D$56>0,K81,0) -> 48 | L56: =IF($D$56>0,L81,0) -> 48 | M56: =IF($D$56>0,M81,0) -> 48 | N56: =IF($D$56>0,N81,0) -> 48 | O56: =IF($D$56>0,O81,0) -> 48 | ... Q56: =IF($D$56>0,Q81,0) -> 48
D57: Non-US | I57: =I52*I42 -> 44.5625 | J57: =J52*J42 -> 142.6 | K57: =K52*K42 -> 258.4625 | L57: =L52*L42 -> 258.4625 | M57: =M52*M42 -> 249.55 | N57: =N52*N42 -> 249.55 | O57: =O52*O42 -> 249.55 | P57: =P52*P42 -> 249.55 | Q57: =Q52*Q42 -> 249.55
D58: Total | H58: =SUM(H55:H57) -> 64.666667 | I58: =SUM(I55:I57) -> 212.69583 | J58: =SUM(J55:J57) -> 420.66667 | K58: =SUM(K55:K57) -> 568.8625 | L58: =SUM(L55:L57) -> 568.8625 | M58: =SUM(M55:M57) -> 559.95 | N58: =SUM(N55:N57) -> 559.95 | O58: =SUM(O55:O57) -> 559.95 | ... Q58: =SUM(Q55:Q57) -> 559.95
B60: Total US and Non-US | H60: =H47 -> 71.165835 | I60: =I47 -> 444.21451 | J60: =J47 -> 1040.36 | K60: =K47 -> 1859.3653 | L60: =L47 -> 2490.7782 | M60: =M47 -> 3065.548 | N60: =N47 -> 3635.2904 | O60: =O47 -> 4137.5167 | ... Q60: =Q47 -> 4972.515
C61: S&M % of sales | H61: =H55/H35 -> 0.76815886 | I61: =I55/I35 -> 0.36382964 | J61: =J55/J35 -> 0.34733409 | K61: =K55/K35 -> 0.22904692 | L61: =L55/L35 -> 0.17783891 | M61: =M55/M35 -> 0.1469724 | N61: =N55/N35 -> 0.12333327 | O61: =O55/O35 -> 0.10913817 | ... Q61: =Q55/Q35 -> 0.090425481
C62: S&M % of sales | I62: =I57/I43 -> 0.83208093 | J62: =J57/J43 -> 0.39220431 | K62: =K57/K43 -> 0.36211984 | L62: =L57/L43 -> 0.25457123 | M62: =M57/M43 -> 0.1949337 | N62: =N57/N43 -> 0.16551462 | O62: =O57/O43 -> 0.14398015 | P62: =P57/P43 -> 0.12793756 | Q62: =Q57/Q43 -> 0.12051608
C63: S&M % of sales | H63: =H58/H60 -> 0.90867573 | I63: =I58/I60 -> 0.47881334 | J63: =J58/J60 -> 0.40434723 | K63: =K58/K60 -> 0.30594445 | L63: =L58/L60 -> 0.22838745 | M63: =M58/M60 -> 0.18265902 | N63: =N58/N60 -> 0.15403171 | O63: =O58/O60 -> 0.1353348 | ... Q63: =Q58/Q60 -> 0.11260901
A65: Co-commercialisation in US
C66: Licensee | E66: =E54 -> 2009 | F66: =E66+1 -> 2010 | G66: =F66+1 -> 2011 | H66: =G66+1 -> 2012 | I66: =H66+1 -> 2013 | J66: =I66+1 -> 2014 | K66: =J66+1 -> 2015 | L66: =K66+1 -> 2016 | M66: =L66+1 -> 2017 | ... Q66: =P66+1 -> 2021
C67: Sales forecast $m | H67: =Sales!J38 -> 71.165835 | I67: =Sales!K38 -> 390.65902 | J67: =Sales!L38 -> 676.77395 | K67: =Sales!M38 -> 1145.6168 | L67: =Sales!N38 -> 1475.4927 | M67: =Sales!O38 -> 1785.3692 | N67: =Sales!P38 -> 2127.5686 | O67: =Sales!Q38 -> 2404.2916 | ... Q67: =Sales!S38 -> 2901.8369
C68: Sales with co-commercialisation $m | H68: =Sales!J78 -> 71.165835 | I68: =Sales!K78 -> 390.65902 | J68: =Sales!L78 -> 676.77395 | K68: =Sales!M78 -> 1145.6168 | L68: =Sales!N78 -> 1475.4927 | M68: =Sales!O78 -> 1785.3692 | N68: =Sales!P78 -> 2127.5686 | O68: =Sales!Q78 -> 2404.2916 | ... Q68: =Sales!S78 -> 2901.8369
C69: Incremental sales $m | H69: =H67-H68 -> 0 | I69: =I67-I68 -> 0 | J69: =J67-J68 -> 0 | K69: =K67-K68 -> 0 | L69: =L67-L68 -> 0 | M69: =M67-M68 -> 0 | N69: =N67-N68 -> 0 | O69: =O67-O68 -> 0 | ... Q69: =Q67-Q68 -> 0
C70: Gross profit forecast $m | H70: ='Lee & Lor'!H9 -> 65.74056 | I70: ='Lee & Lor'!I9 -> 360.87742 | J70: ='Lee & Lor'!J9 -> 625.18059 | K70: ='Lee & Lor'!K9 -> 1075.1903 | L70: ='Lee & Lor'!L9 -> 1384.7872 | M70: ='Lee & Lor'!M9 -> 1675.6141 | N70: ='Lee & Lor'!N9 -> 1996.7769 | O70: ='Lee & Lor'!O9 -> 2256.4885 | ... Q70: ='Lee & Lor'!Q9 -> 2723.4473
C71: Gross profit with co-commercialisation $m | H71: =Sales!J82 -> 65.74056 | I71: =Sales!K82 -> 360.87742 | J71: =Sales!L82 -> 625.18059 | K71: =Sales!M82 -> 1075.1903 | L71: =Sales!N82 -> 1384.7872 | M71: =Sales!O82 -> 1675.6141 | N71: =Sales!P82 -> 1996.7769 | O71: =Sales!Q82 -> 2256.4885 | ... Q71: =Sales!S82 -> 2723.4473
C72: Incremental gross profit $m | H72: =H70-H71 -> 0 | I72: =I70-I71 -> 0 | J72: =J70-J71 -> 0 | K72: =K70-K71 -> 0 | L72: =L70-L71 -> 0 | M72: =M70-M71 -> 0 | N72: =N70-N71 -> 0 | O72: =O70-O71 -> 0 | ... Q72: =Q70-Q71 -> 0
C73: Less profit share $m | D73: =Control!I16 -> 0.5 | H73: =$D$73*H72 -> 0 | I73: =$D$73*I72 -> 0 | J73: =$D$73*J72 -> 0 | K73: =$D$73*K72 -> 0 | L73: =$D$73*L72 -> 0 | M73: =$D$73*M72 -> 0 | N73: =$D$73*N72 -> 0 | O73: =$D$73*O72 -> 0 | ... Q73: =$D$73*Q72 -> 0
C74: Net incremental gross profit $m | H74: =H72-H73 -> 0 | I74: =I72-I73 -> 0 | J74: =J72-J73 -> 0 | K74: =K72-K73 -> 0 | L74: =L72-L73 -> 0 | M74: =M72-M73 -> 0 | N74: =N72-N73 -> 0 | O74: =O72-O73 -> 0 | ... Q74: =Q72-Q73 -> 0
C76: Volume of calls 000 | D76: No of reps | E76: =IF($D$73>0,100,0) -> 100 | F76: Calls/rep/pa | G76: =D9 -> 600 | H76: =$E$76*$G$76/1000*H51 -> 30 | I76: =$E$76*$G$76/1000*I51 -> 78 | J76: =$E$76*$G$76/1000*J51 -> 129 | K76: =$E$76*$G$76/1000*K51 -> 144 | L76: =$E$76*$G$76/1000*L51 -> 144 | M76: =$E$76*$G$76/1000*M51 -> 144 | N76: =$E$76*$G$76/1000*N51 -> 144 | O76: =$E$76*$G$76/1000*O51 -> 144 | ... Q76: =$E$76*$G$76/1000*Q51 -> 144
C77: Fees payable to Licensor $m | D77: Fee per call | E77: =Control!I17 -> 500 | H77: =H76*$E$77/1000 -> 15 | I77: =I76*$E$77/1000 -> 39 | J77: =J76*$E$77/1000 -> 64.5 | K77: =K76*$E$77/1000 -> 72 | L77: =L76*$E$77/1000 -> 72 | M77: =M76*$E$77/1000 -> 72 | N77: =N76*$E$77/1000 -> 72 | O77: =O76*$E$77/1000 -> 72 | ... Q77: =Q76*$E$77/1000 -> 72
C78: Net incremental profit to Licensee $m | E78: =Control!G45 -> 0.12 | F78: NPV $m | G78: =NPV(E78,H78:Q78) -> -324.27745 | H78: =H74-H77 -> -15 | I78: =I74-I77 -> -39 | J78: =J74-J77 -> -64.5 | K78: =K74-K77 -> -72 | L78: =L74-L77 -> -72 | M78: =M74-M77 -> -72 | N78: =N74-N77 -> -72 | O78: =O74-O77 -> -72 | ... Q78: =Q74-Q77 -> -72
C80: Licensor
C81: Cost of salesforce $m | D81: No of reps | E81: =E76 -> 100 | F81: Cost/rep $k | G81: =D11 -> 200 | H81: =$E$81*$G$81/1000*H51 -> 10 | I81: =$E$81*$G$81/1000*I51 -> 26 | J81: =$E$81*$G$81/1000*J51 -> 43 | K81: =$E$81*$G$81/1000*K51 -> 48 | L81: =$E$81*$G$81/1000*L51 -> 48 | M81: =$E$81*$G$81/1000*M51 -> 48 | N81: =$E$81*$G$81/1000*N51 -> 48 | O81: =$E$81*$G$81/1000*O51 -> 48 | ... Q81: =$E$81*$G$81/1000*Q51 -> 48
C82: Volume of calls 000 | D82: No of reps | E82: 100 | F82: Calls/rep/pa | G82: =G76 -> 600 | H82: =H76 -> 30 | I82: =I76 -> 78 | J82: =J76 -> 129 | K82: =K76 -> 144 | L82: =L76 -> 144 | M82: =M76 -> 144 | N82: =N76 -> 144 | ... Q82: =Q76 -> 144
C83: Fee per call | H83: =H81*1000/H82 -> 333.33333 | I83: =I81*1000/I82 -> 333.33333 | J83: =J81*1000/J82 -> 333.33333 | K83: =K81*1000/K82 -> 333.33333 | L83: =L81*1000/L82 -> 333.33333 | M83: =M81*1000/M82 -> 333.33333 | N83: =N81*1000/N82 -> 333.33333 | O83: =O81*1000/O82 -> 333.33333 | ... Q83: =Q81*1000/Q82 -> 333.33333
C85: Salesforce fees received from Licensee $m | H85: =H77 -> 15 | I85: =I77 -> 39 | J85: =J77 -> 64.5 | K85: =K77 -> 72 | L85: =L77 -> 72 | M85: =M77 -> 72 | N85: =N77 -> 72 | O85: =O77 -> 72 | ... Q85: =Q77 -> 72
C86: Incremental cost / profit to Licensee from salesforce $m | H86: =H85-H81 -> 5 | I86: =I85-I81 -> 13 | J86: =J85-J81 -> 21.5 | K86: =K85-K81 -> 24 | L86: =L85-L81 -> 24 | M86: =M85-M81 -> 24 | N86: =N85-N81 -> 24 | O86: =O85-O81 -> 24 | ... Q86: =Q85-Q81 -> 24
C87: Incremental profit share $m | H87: =H73 -> 0 | I87: =I73 -> 0 | J87: =J73 -> 0 | K87: =K73 -> 0 | L87: =L73 -> 0 | M87: =M73 -> 0 | N87: =N73 -> 0 | O87: =O73 -> 0 | ... Q87: =Q73 -> 0
C88: Net incremental profit to Licensor $m | E88: =E78 -> 0.12 | F88: NPV $m | G88: =NPV(E88,H88:Q88) -> 432.36993 | H88: =SUM(H85:H87) -> 20 | I88: =SUM(I85:I87) -> 52 | J88: =SUM(J85:J87) -> 86 | K88: =SUM(K85:K87) -> 96 | L88: =SUM(L85:L87) -> 96 | M88: =SUM(M85:M87) -> 96 | N88: =SUM(N85:N87) -> 96 | O88: =SUM(O85:O87) -> 96 | ... Q88: =SUM(Q85:Q87) -> 96
C91: Cost of salesforce $m | D91: No of reps | E91: 100 | F91: Cost/rep $k | G91: 200 | H91: =$E$91*$G$91*H51/1000 -> 10 | I91: =$E$91*$G$91*I51/1000 -> 26 | J91: =$E$91*$G$91*J51/1000 -> 43 | K91: =$E$91*$G$91*K51/1000 -> 48 | L91: =$E$91*$G$91*L51/1000 -> 48 | M91: =$E$91*$G$91*M51/1000 -> 48 | N91: =$E$91*$G$91*N51/1000 -> 48 | O91: =$E$91*$G$91*O51/1000 -> 48 | ... Q91: =$E$91*$G$91*Q51/1000 -> 48
C94: US | H94: 44.454 | I94: 120.553 | J94: 161.865 | K94: 187.504 | L94: 187.504 | M94: 187.504 | N94: 187.504 | O94: 187.504 | P94: 187.504 | Q94: 187.504
C95: US | H95: 6.856 | I95: 23.946 | J95: 72.2 | K95: 75 | L95: 75 | M95: 75 | N95: 75 | O95: 75 | P95: 75 | Q95: 75
C96: Total US actual | H96: =H94+H95 -> 51.31 | I96: =I94+I95 -> 144.499 | J96: =J94+J95 -> 234.065 | K96: =K94+K95 -> 262.504 | L96: =L94+L95 -> 262.504 | M96: =M94+M95 -> 262.504 | N96: =N94+N95 -> 262.504 | O96: =O94+O95 -> 262.504 | ... Q96: =Q94+Q95 -> 262.504
C97: Total US model | H97: =H55-H96 -> 3.3566667 | I97: =I55-I96 -> -2.3656667 | J97: =J55-J96 -> 1.0016667 | K97: =K55-K96 -> -0.104 | L97: =L55-L96 -> -0.104 | M97: =M55-M96 -> -0.104 | N97: =N55-N96 -> -0.104 | O97: =O55-O96 -> -0.104 | ... Q97: =Q55-Q96 -> -0.104
C98: Non-US | I98: 40.627676 | J98: 141.50171 | K98: 259.73208 | L98: 260 | M98: 250 | N98: 250 | O98: 250 | P98: 250 | Q98: 250
C99: Actual forecast | H99: =H96+H98 -> 51.31 | I99: =I96+I98 -> 185.12668 | J99: =J96+J98 -> 375.56671 | K99: =K96+K98 -> 522.23608 | L99: =L96+L98 -> 522.504 | M99: =M96+M98 -> 512.504 | N99: =N96+N98 -> 512.504 | O99: =O96+O98 -> 512.504 | ... Q99: =Q96+Q98 -> 512.504
C100: Model above | H100: =H58 -> 64.666667 | I100: =I46 -> 287.58333 | J100: =J46 -> 287.58333 | K100: =K46 -> 287.58333 | L100: =L46 -> 287.58333 | M100: =M46 -> 287.58333 | N100: =N46 -> 287.58333 | O100: =O46 -> 287.58333 | P100: =P46 -> 287.58333 | Q100: =Q46 -> 287.58333

Sheet Project
A1: PROJECT P&L AND CASH FLOW | E1: Assumptions in red | H1: Assumptions in yellow box from control panel
R3: Terminal
B4: Years from first launch | H4: 1 | I4: =H4+1 -> 2 | J4: =I4+1 -> 3 | K4: =J4+1 -> 4 | L4: =K4+1 -> 5 | M4: =L4+1 -> 6 | N4: =M4+1 -> 7 | O4: =N4+1 -> 8 | P4: =O4+1 -> 9 | Q4: =P4+1 -> 10 | R4: value
B5: Years from signature | E5: 0 | F5: 1 | G5: =F5+1 -> 2 | H5: =G5+1 -> 3 | I5: =H5+1 -> 4 | J5: =I5+1 -> 5 | K5: =J5+1 -> 6 | L5: =K5+1 -> 7 | M5: =L5+1 -> 8 | N5: =M5+1 -> 9 | ... Q5: =P5+1 -> 12 | R5: x sales
E6: =Control!M5 -> 2009 | F6: =E6+1 -> 2010 | G6: =F6+1 -> 2011 | H6: =G6+1 -> 2012 | I6: =H6+1 -> 2013 | J6: =I6+1 -> 2014 | K6: =J6+1 -> 2015 | L6: =K6+1 -> 2016 | M6: =L6+1 -> 2017 | ... Q6: =P6+1 -> 2021
R7: 3
A8: Total sales $m | D8: Sales | H8: =Sales!J40 -> 71.165835 | I8: =Sales!K40 -> 444.21451 | J8: =Sales!L40 -> 1040.36 | K8: =Sales!M40 -> 1859.3653 | L8: =Sales!N40 -> 2490.7782 | M8: =Sales!O40 -> 3065.548 | N8: =Sales!P40 -> 3635.2904 | O8: =Sales!Q40 -> 4137.5167 | ... Q8: =Sales!S40 -> 4972.515 | R8: =R7*Q8 -> 14917.545
A9: Costs of goods sold
B10: Cost of goods | D10: COG | E10: =COG!F59 -> 0 | F10: =COG!G59 -> 0 | G10: =COG!H59 -> 0 | H10: =COG!I59 -> 3.2903 | I10: =COG!J59 -> 24.939397 | J10: =COG!K59 -> 77.981651 | K10: =COG!L59 -> 98.456435 | L10: =COG!M59 -> 135.20064 | ... Q10: =COG!R59 -> 272.36064
B11: Distribution (% sales) | D11: 0.03 | E11: =$D$11*E8 -> 0 | F11: =$D$11*F8 -> 0 | G11: =$D$11*G8 -> 0 | H11: =$D$11*H8 -> 2.134975 | I11: =$D$11*I8 -> 13.326435 | J11: =$D$11*J8 -> 31.210799 | K11: =$D$11*K8 -> 55.78096 | L11: =$D$11*L8 -> 74.723347 | ... Q11: =$D$11*Q8 -> 149.17545
A12: Gross profit | E12: =E8-E10-E11 -> 0 | F12: =F8-F10-F11 -> 0 | G12: =G8-G10-G11 -> 0 | H12: =H8-H10-H11 -> 65.74056 | I12: =I8-I10-I11 -> 405.94868 | J12: =J8-J10-J11 -> 931.16751 | K12: =K8-K10-K11 -> 1705.1279 | L12: =L8-L10-L11 -> 2280.8543 | ... Q12: =Q8-Q10-Q11 -> 4550.9789 | R12: =R8 -> 14917.545
B13: Royalties payable (University) | D13: =Control!S13 -> 0.04 | E13: =$D$13*E8 -> 0 | F13: =$D$13*F8 -> 0 | G13: =$D$13*G8 -> 0 | H13: =$D$13*H8 -> 2.8466334 | I13: =$D$13*I8 -> 17.76858 | J13: =$D$13*J8 -> 41.614398 | K13: =$D$13*K8 -> 74.374613 | L13: =$D$13*L8 -> 99.63113 | ... Q13: =$D$13*Q8 -> 198.9006
B14: R&D | D14: R&D | E14: ='R&D'!I46 -> 18.924655 | F14: ='R&D'!J46 -> 56.540766 | G14: ='R&D'!K46 -> 86.296869 | H14: ='R&D'!L46 -> 110.10111 | I14: ='R&D'!M46 -> 117.7122 | J14: ='R&D'!N46 -> 140.43394 | K14: ='R&D'!O46 -> 135.41521 | L14: ='R&D'!P46 -> 84.721067 | ... Q14: ='R&D'!U46 -> 20
B15: Sales and Marketing | D15: S&M | E15: ='S&M'!E58 -> 0 | F15: ='S&M'!F58 -> 0 | G15: ='S&M'!G58 -> 0 | H15: ='S&M'!H58 -> 64.666667 | I15: ='S&M'!I58 -> 212.69583 | J15: ='S&M'!J58 -> 420.66667 | K15: ='S&M'!K58 -> 568.8625 | L15: ='S&M'!L58 -> 568.8625 | ... Q15: ='S&M'!Q58 -> 559.95
B16: General & Administration | D16: 0 | E16: =$D$16*E8 -> 0 | F16: =$D$16*F8 -> 0 | G16: =$D$16*G8 -> 0 | H16: =$D$16*H8 -> 0 | I16: =$D$16*I8 -> 0 | J16: =$D$16*J8 -> 0 | K16: =$D$16*K8 -> 0 | L16: =$D$16*L8 -> 0 | ... Q16: =$D$16*Q8 -> 0
A17: Total operating expenses | E17: =SUM(E13:E16) -> 18.924655 | F17: =SUM(F13:F16) -> 56.540766 | G17: =SUM(G13:G16) -> 86.296869 | H17: =SUM(H13:H16) -> 177.61441 | I17: =SUM(I13:I16) -> 348.17661 | J17: =SUM(J13:J16) -> 602.715 | K17: =SUM(K13:K16) -> 778.65232 | L17: =SUM(L13:L16) -> 753.2147 | ... R17: =SUM(R13:R16) -> 0
A18: Operating income / (loss) EBITDA | E18: =E12-E17 -> -18.924655 | F18: =F12-F17 -> -56.540766 | G18: =G12-G17 -> -86.296869 | H18: =H12-H17 -> -111.87385 | I18: =I12-I17 -> 57.772067 | J18: =J12-J17 -> 328.45251 | K18: =K12-K17 -> 926.47561 | L18: =L12-L17 -> 1527.6396 | ... R18: =R12-R17 -> 14917.545
B19: Depreciation & amortisation | D19: Ignored
B20: Tax | D20: Ignored
A21: Post tax profit | E21: =E18 -> -18.924655 | F21: =F18 -> -56.540766 | G21: =G18 -> -86.296869 | H21: =H18 -> -111.87385 | I21: =I18 -> 57.772067 | J21: =J18 -> 328.45251 | K21: =K18 -> 926.47561 | L21: =L18 -> 1527.6396 | ... R21: =R18 -> 14917.545
B22: Depreciation & amortisation
B23: Working capital movement
B24: Capital expenditure on manufacture
A25: Cash flow | E25: =E21+SUM(E22:E24) -> -18.924655 | F25: =F21+SUM(F22:F24) -> -56.540766 | G25: =G21+SUM(G22:G24) -> -86.296869 | H25: =H21+SUM(H22:H24) -> -111.87385 | I25: =I21+SUM(I22:I24) -> 57.772067 | J25: =J21+SUM(J22:J24) -> 328.45251 | K25: =K21+SUM(K22:K24) -> 926.47561 | L25: =L21+SUM(L22:L24) -> 1527.6396 | ... Q25: =Q21+SUM(Q22:Q24) -> 3772.1283 | R25: =R21+R22+R23+R24 -> 14917.545
A27: Payback | C27: Cumulative undiscounted cash flow | E27: =E25 -> -18.924655 | F27: =F25+E27 -> -75.465421 | G27: =G25+F27 -> -161.76229 | H27: =H25+G27 -> -273.63614 | I27: =I25+H27 -> -215.86407 | J27: =J25+I27 -> 112.58844 | K27: =K25+J27 -> 1039.0641 | L27: =L25+K27 -> 2566.7036 | M27: =M25+L27 -> 4635.2298 | ... Q27: =Q25+P27 -> 17523.272 | R27: =R25 -> 14917.545
D28: Years from signature | E28: =MATCH(0,$F$27:$Q$27,1) -> 4
A30: NPV of project excl sunk costs | D30: Cash flow | E30: =E25 -> -18.924655 | F30: =F25 -> -56.540766 | G30: =G25 -> -86.296869 | H30: =H25 -> -111.87385 | I30: =I25 -> 57.772067 | J30: =J25 -> 328.45251 | K30: =K25 -> 926.47561 | L30: =L25 -> 1527.6396 | ... R30: =R25 -> 14917.545
C31: Discount factor | D31: =Control!G45 -> 0.12 | E31: 1 | F31: =E31/(1+$D$31) -> 0.89285714 | G31: =F31/(1+$D$31) -> 0.79719388 | H31: =G31/(1+$D$31) -> 0.71178025 | I31: =H31/(1+$D$31) -> 0.63551808 | J31: =I31/(1+$D$31) -> 0.56742686 | K31: =J31/(1+$D$31) -> 0.50663112 | L31: =K31/(1+$D$31) -> 0.45234922 | M31: =L31/(1+$D$31) -> 0.40388323 | ... R31: =Q31/(1+$D$31) -> 0.22917419
C32: Discounted cash | E32: =E30*E31 -> -18.924655 | F32: =F30*F31 -> -50.482827 | G32: =G30*G31 -> -68.795336 | H32: =H30*H31 -> -79.629593 | I32: =I30*I31 -> 36.715193 | J32: =J30*J31 -> 186.37277 | K32: =K30*K31 -> 469.38138 | L32: =L30*L31 -> 691.02655 | ... R32: =R30*R31 -> 3418.7163
C33: Sum discounted cash | D33: $m | E33: =SUM(E32:R32) -> 9302.5829 | F33: to 2021 incl terminal value | J33: =SUM(E32:Q32) -> 5883.8666 | K33: to 2020 excl TV | P33: Terminal value | Q33: =E33-J33 -> 3418.7163
C34: Excel formula calc | D34: $m | E34: =NPV(D31,F30:R30)+E30 -> 9302.5829 | F34: to 2021 incl terminal value | J34: =NPV(D31,F30:Q30)+E30 -> 5883.8666 | K34: to 2020 excl TV | P34: Terminal value % of total | Q34: =Q33/E33 -> 0.36750184
C36: Internal rate of return | E36: =IRR(E30:R30) -> 0.89626858
A38: NPV of project including sunk costs
B39: Cash Flow incl sunk costs | E39: =-'Lor Financials'!D44 -> -17.194 | F39: =F25 -> -56.540766 | G39: =G25 -> -86.296869 | H39: =H25 -> -111.87385 | I39: =I25 -> 57.772067 | J39: =J25 -> 328.45251 | K39: =K25 -> 926.47561 | L39: =L25 -> 1527.6396 | M39: =M25 -> 2068.5262 | ... R39: =R25 -> 14917.545
B40: NPV | D40: =D31 -> 0.12 | E40: =NPV(D40,F39:R39)+E39 -> 9304.3135
B41: IRR | E41: =IRR(E39:R39) -> 0.90264674
A44: Working capital calculation | F44: =F6 -> 2010 | G44: =G6 -> 2011 | H44: =H6 -> 2012 | I44: =I6 -> 2013 | J44: =J6 -> 2014 | K44: =K6 -> 2015 | L44: =L6 -> 2016 | M44: =M6 -> 2017 | ... Q44: =Q6 -> 2021
B45: Receivables/debtors | D45: days sales outstanding | E45: 30 | F45: =F8/365*$E$45 -> 0 | G45: =G8/365*$E$45 -> 0 | H45: =H8/365*$E$45 -> 5.8492467 | I45: =I8/365*$E$45 -> 36.510782 | J45: =J8/365*$E$45 -> 85.509038 | K45: =K8/365*$E$45 -> 152.82455 | L45: =L8/365*$E$45 -> 204.7215 | M45: =M8/365*$E$45 -> 251.96285 | ... Q45: =Q8/365*$E$45 -> 408.69986
B46: Inventory/stock | D46: months of cost of goods | E46: 3 | F46: =F10/12*$E$46 -> 0 | G46: =G10/12*$E$46 -> 0 | H46: =H10/12*$E$46 -> 0.82257499 | I46: =I10/12*$E$46 -> 6.2348493 | J46: =J10/12*$E$46 -> 19.495413 | K46: =K10/12*$E$46 -> 24.614109 | L46: =L10/12*$E$46 -> 33.80016 | M46: =M10/12*$E$46 -> 42.02796 | ... Q46: =Q10/12*$E$46 -> 68.09016
B47: Payables/creditors | D47: days credt taken | E47: 30 | F47: =-F17/365*$E$47 -> -4.6471862 | G47: =-G17/365*$E$47 -> -7.0928934 | H47: =-H17/365*$E$47 -> -14.598444 | I47: =-I17/365*$E$47 -> -28.617256 | J47: =-J17/365*$E$47 -> -49.53822 | K47: =-K17/365*$E$47 -> -63.998821 | L47: =-L17/365*$E$47 -> -61.908057 | M47: =-M17/365*$E$47 -> -60.570707 | ... Q47: =-Q17/365*$E$47 -> -64.015118
B48: Year end working capital balance | F48: =F46+F45+F47 -> -4.6471862 | G48: =G46+G45+G47 -> -7.0928934 | H48: =H46+H45+H47 -> -7.9266226 | I48: =I46+I45+I47 -> 14.128375 | J48: =J46+J45+J47 -> 55.466231 | K48: =K46+K45+K47 -> 113.43984 | L48: =L46+L45+L47 -> 176.6136 | M48: =M46+M45+M47 -> 233.42011 | ... Q48: =Q46+Q45+Q47 -> 412.7749
B49: Movement in working capital | F49: =E48-F48 -> 4.6471862 | G49: =F48-G48 -> 2.4457071 | H49: =G48-H48 -> 0.83372923 | I49: =H48-I48 -> -22.054998 | J49: =I48-J48 -> -41.337856 | K49: =J48-K48 -> -57.973604 | L49: =K48-L48 -> -63.173766 | M49: =L48-M48 -> -56.806504 | ... Q49: =P48-Q48 -> -29.549534
D50: WC % of sales | H50: =H48/H8 -> -0.11138242 | I50: =I48/I8 -> 0.031805299 | J50: =J48/J8 -> 0.053314462 | K50: =K48/K8 -> 0.061009977 | L50: =L48/L8 -> 0.070906996 | M50: =M48/M8 -> 0.076143027 | N50: =N48/N8 -> 0.079073041 | O50: =O48/O8 -> 0.081111393 | ... Q50: =Q48/Q8 -> 0.083011294

Sheet Lee & Lor
A1: LICENSEE AND LICENSOR PROJECT VALUATIONS | F1: 1 | G1: =F1+1 -> 2 | H1: =G1+1 -> 3 | I1: =H1+1 -> 4 | J1: =I1+1 -> 5 | K1: =J1+1 -> 6 | L1: =K1+1 -> 7 | M1: =L1+1 -> 8 | N1: =M1+1 -> 9 | ... Q1: =P1+1 -> 12 | R1: Terminal
D2: =Control!Y2 -> 2008 | R2: value
A3: LICENSEE VALUATION | D3: $m | E3: =D2+1 -> 2009 | F3: =E3+1 -> 2010 | G3: =F3+1 -> 2011 | H3: =G3+1 -> 2012 | I3: =H3+1 -> 2013 | J3: =I3+1 -> 2014 | K3: =J3+1 -> 2015 | L3: =K3+1 -> 2016 | M3: =L3+1 -> 2017 | ... Q3: =P3+1 -> 2021 | R3: =Project!R7 -> 3
B4: Total Sales | H4: =H6+H13 -> 71.165835 | I4: =I6+I13 -> 444.21451 | J4: =J6+J13 -> 1040.36 | K4: =K6+K13 -> 1859.3653 | L4: =L6+L13 -> 2490.7782 | M4: =M6+M13 -> 3065.548 | N4: =N6+N13 -> 3635.2904 | O4: =O6+O13 -> 4137.5167 | ... Q4: =Q6+Q13 -> 4972.515 | R4: =R3*Q4 -> 14917.545
C5: US
B6: Sales | H6: =Sales!J38 -> 71.165835 | I6: =Sales!K38 -> 390.65902 | J6: =Sales!L38 -> 676.77395 | K6: =Sales!M38 -> 1145.6168 | L6: =Sales!N38 -> 1475.4927 | M6: =Sales!O38 -> 1785.3692 | N6: =Sales!P38 -> 2127.5686 | O6: =Sales!Q38 -> 2404.2916 | ... Q6: =Sales!S38 -> 2901.8369
C7: Cost of goods sold | E7: =COG!F60 -> 0 | F7: =COG!G60 -> 0 | G7: =COG!H60 -> 0 | H7: =COG!I60 -> 3.2903 | I7: =COG!J60 -> 18.061832 | J7: =COG!K60 -> 31.290145 | K7: =COG!L60 -> 36.05797 | L7: =COG!M60 -> 46.440721 | ... Q7: =COG!R60 -> 91.334511
C8: Distribution | D8: 0.03 | E8: =$D$8*E6 -> 0 | F8: =$D$8*F6 -> 0 | G8: =$D$8*G6 -> 0 | H8: =$D$8*H6 -> 2.134975 | I8: =$D$8*I6 -> 11.719771 | J8: =$D$8*J6 -> 20.303218 | K8: =$D$8*K6 -> 34.368504 | L8: =$D$8*L6 -> 44.26478 | ... Q8: =$D$8*Q6 -> 87.055108
B9: Gross profit | E9: =E6-SUM(E7:E8) -> 0 | F9: =F6-SUM(F7:F8) -> 0 | G9: =G6-SUM(G7:G8) -> 0 | H9: =H6-SUM(H7:H8) -> 65.74056 | I9: =I6-SUM(I7:I8) -> 360.87742 | J9: =J6-SUM(J7:J8) -> 625.18059 | K9: =K6-SUM(K7:K8) -> 1075.1903 | L9: =L6-SUM(L7:L8) -> 1384.7872 | ... Q9: =Q6-SUM(Q7:Q8) -> 2723.4473
C10: Sales and Marketing | E10: ='S&M'!E55 -> 0 | F10: ='S&M'!F55 -> 0 | G10: ='S&M'!G55 -> 0 | H10: ='S&M'!H55 -> 54.666667 | I10: ='S&M'!I55 -> 142.13333 | J10: ='S&M'!J55 -> 235.06667 | K10: ='S&M'!K55 -> 262.4 | L10: ='S&M'!L55 -> 262.4 | ... Q10: ='S&M'!Q55 -> 262.4
B11: US profit contribution | E11: =E9-E10 -> 0 | F11: =F9-F10 -> 0 | G11: =G9-G10 -> 0 | H11: =H9-H10 -> 11.073893 | I11: =I9-I10 -> 218.74409 | J11: =J9-J10 -> 390.11392 | K11: =K9-K10 -> 812.79033 | L11: =L9-L10 -> 1122.3872 | ... Q11: =Q9-Q10 -> 2461.0473
C12: NON-US
B13: Sales | H13: =Sales!J39 -> 0 | I13: =Sales!K39 -> 53.555488 | J13: =Sales!L39 -> 363.58601 | K13: =Sales!M39 -> 713.74853 | L13: =Sales!N39 -> 1015.2856 | M13: =Sales!O39 -> 1280.1789 | N13: =Sales!P39 -> 1507.7218 | O13: =Sales!Q39 -> 1733.2251 | ... Q13: =Sales!S39 -> 2070.6781
C14: Cost of goods sold | H14: =COG!I61 -> 0 | I14: =COG!J61 -> 6.8775649 | J14: =COG!K61 -> 46.691506 | K14: =COG!L61 -> 62.398465 | L14: =COG!M61 -> 88.759919 | M14: =COG!N61 -> 111.91784 | N14: =COG!O61 -> 131.81046 | O14: =COG!P61 -> 151.52477 | ... Q14: =COG!R61 -> 181.02613
C15: Distribution | D15: 0.03 | E15: =$D$8*E13 -> 0 | F15: =$D$8*F13 -> 0 | G15: =$D$8*G13 -> 0 | H15: =$D$8*H13 -> 0 | I15: =$D$8*I13 -> 1.6066646 | J15: =$D$8*J13 -> 10.90758 | K15: =$D$8*K13 -> 21.412456 | L15: =$D$8*L13 -> 30.458567 | ... Q15: =$D$8*Q13 -> 62.120342
B16: Gross profit | E16: =E13-SUM(E14:E15) -> 0 | F16: =F13-SUM(F14:F15) -> 0 | G16: =G13-SUM(G14:G15) -> 0 | H16: =H13-SUM(H14:H15) -> 0 | I16: =I13-SUM(I14:I15) -> 45.071258 | J16: =J13-SUM(J14:J15) -> 305.98692 | K16: =K13-SUM(K14:K15) -> 629.93761 | L16: =L13-SUM(L14:L15) -> 896.0671 | ... Q16: =Q13-SUM(Q14:Q15) -> 1827.5316
C17: Sales and Marketing | E17: ='S&M'!E57 -> 0 | F17: ='S&M'!F57 -> 0 | G17: ='S&M'!G57 -> 0 | H17: ='S&M'!H57 -> 0 | I17: ='S&M'!I57 -> 44.5625 | J17: ='S&M'!J57 -> 142.6 | K17: ='S&M'!K57 -> 258.4625 | L17: ='S&M'!L57 -> 258.4625 | ... Q17: ='S&M'!Q57 -> 249.55
B18: Non US profit contribution | E18: =E16-E17 -> 0 | F18: =F16-F17 -> 0 | G18: =G16-G17 -> 0 | H18: =H16-H17 -> 0 | I18: =I16-I17 -> 0.50875825 | J18: =J16-J17 -> 163.38692 | K18: =K16-K17 -> 371.47511 | L18: =L16-L17 -> 637.6046 | ... Q18: =Q16-Q17 -> 1577.9816
C19: R&D | E19: ='R&D'!I37 -> 16.474655 | F19: ='R&D'!J37 -> 53.840766 | G19: ='R&D'!K37 -> 82.946869 | H19: ='R&D'!L37 -> 105.06947 | I19: ='R&D'!M37 -> 110.82753 | J19: ='R&D'!N37 -> 132.69908 | K19: ='R&D'!O37 -> 128.50458 | L19: ='R&D'!P37 -> 83.266347 | ... Q19: ='R&D'!U37 -> 20
C20: G&A | D20: 0 | H20: =$D$20*(H13+H6) -> 0 | I20: =$D$20*(I13+I6) -> 0 | J20: =$D$20*(J13+J6) -> 0 | K20: =$D$20*(K13+K6) -> 0 | L20: =$D$20*(L13+L6) -> 0 | M20: =$D$20*(M13+M6) -> 0 | N20: =$D$20*(N13+N6) -> 0 | O20: =$D$20*(O13+O6) -> 0 | ... Q20: =$D$20*(Q13+Q6) -> 0
B21: Operating profit pre deal terms | E21: =E11+E18-E19-E20 -> -16.474655 | F21: =F11+F18-F19-F20 -> -53.840766 | G21: =G11+G18-G19-G20 -> -82.946869 | H21: =H11+H18-H19-H20 -> -93.995572 | I21: =I11+I18-I19-I20 -> 108.42532 | J21: =J11+J18-J19-J20 -> 420.80177 | K21: =K11+K18-K19-K20 -> 1055.7609 | L21: =L11+L18-L19-L20 -> 1676.7254 | ... Q21: =Q11+Q18-Q19-Q20 -> 4019.0289 | R21: =R4 -> 14917.545
C22: Milestone payments | E22: =Control!M40 -> 150 | F22: =Control!N40 -> 35 | G22: =Control!O40 -> 0 | H22: =Control!P40 -> 55 | I22: =Control!Q40 -> 45 | J22: =Control!R40 -> 325 | K22: =Control!S40 -> 175 | L22: =Control!T40 -> 0 | ... Q22: =Control!Y40 -> 0
C23: Royalty payable to Licensor | H23: =H71 -> 7.1165835 | I23: =I71 -> 45.305741 | J23: =J71 -> 121.65039 | K23: =K71 -> 185.49845 | L23: =L71 -> 286.52452 | M23: =M71 -> 378.48769 | N23: =N71 -> 469.64646 | O23: =O71 -> 550.00267 | ... Q23: =Q71 -> 683.6024
C24: Payment for Licensor salesforce | H24: ='S&M'!H77 -> 15 | I24: ='S&M'!I77 -> 39 | J24: ='S&M'!J77 -> 64.5 | K24: ='S&M'!K77 -> 72 | L24: ='S&M'!L77 -> 72 | M24: ='S&M'!M77 -> 72 | N24: ='S&M'!N77 -> 72 | O24: ='S&M'!O77 -> 72 | ... Q24: ='S&M'!Q77 -> 72
C25: US profit share | D25: =Control!I16 -> 0.5 | H25: =$D$25*H11 -> 5.5369466 | I25: =$D$25*I11 -> 109.37204 | J25: =$D$25*J11 -> 195.05696 | K25: =$D$25*K11 -> 406.39516 | L25: =$D$25*L11 -> 561.19358 | M25: =$D$25*M11 -> 706.60705 | N25: =$D$25*N11 -> 867.18845 | O25: =$D$25*O11 -> 997.04424 | ... Q25: =$D$25*Q11 -> 1230.5237
B26: Operating profit / EBITDA | E26: =E21-SUM(E22:E25) -> -166.47466 | F26: =F21-SUM(F22:F25) -> -88.840766 | G26: =G21-SUM(G22:G25) -> -82.946869 | H26: =H21-SUM(H22:H25) -> -176.6491 | I26: =I21-SUM(I22:I25) -> -130.25247 | J26: =J21-SUM(J22:J25) -> -285.40559 | K26: =K21-SUM(K22:K25) -> 216.86724 | L26: =L21-SUM(L22:L25) -> 757.00731 | ... Q26: =Q21-SUM(Q22:Q25) -> 2032.9029 | R26: =R21-R22-R23 -> 14917.545
C27: Depreciation and amortisation | D27: Ignored
C28: Working capital movement | D28: Ignored
C29: Capital expenditure | F29: =Control!I10*-Control!I11 -> 0 | R29: =Project!R24 -> 0
B30: Cash flow | E30: =SUM(E26:E29) -> -166.47466 | F30: =SUM(F26:F29) -> -88.840766 | G30: =SUM(G26:G29) -> -82.946869 | H30: =SUM(H26:H29) -> -176.6491 | I30: =SUM(I26:I29) -> -130.25247 | J30: =SUM(J26:J29) -> -285.40559 | K30: =SUM(K26:K29) -> 216.86724 | L30: =SUM(L26:L29) -> 757.00731 | ... R30: =SUM(R26:R29) -> 14917.545
B31: NPV incl terminal value | D31: =Control!G45 -> 0.12 | E31: =NPV(D31,F30:R30)+E30 -> 5710.4626 | F31: % total | G31: =E31/(E31+E51) -> 0.60693975 | H31: =NPV($D$31,F30:Q30)+E30 -> 2291.7463 | I31: excl terminal value | M31: Terminal value | N31: =E31-H31 -> 3418.7163 | O31: =N31/E31 -> 0.59867589
B32: IRR incl terminal value | E32: =IRR(E30:R30) -> 0.4492494
B33: Payback | E33: =MATCH(0,$E$30:$R$30,1) -> 6
A35: LICENSOR VALUATION | D35: $m | E35: =E3 -> 2009 | F35: =F3 -> 2010 | G35: =G3 -> 2011 | H35: =H3 -> 2012 | I35: =I3 -> 2013 | J35: =J3 -> 2014 | K35: =K3 -> 2015 | L35: =L3 -> 2016 | ... Q35: =Q3 -> 2021 | R35: Terminal
C36: Milestone receipts | D36: NPV | E36: =E22 -> 150 | F36: =F22 -> 35 | G36: =G22 -> 0 | H36: =H22 -> 55 | I36: =I22 -> 45 | J36: =J22 -> 325 | K36: =K22 -> 175 | L36: =L22 -> 0 | ... Q36: =Q22 -> 0
C37: Royalties received from Licensee | D37: =NPV(D51,F37:S37)+E37 -> 1182.9945 | E37: =E23 -> 0 | F37: =F23 -> 0 | G37: =G23 -> 0 | H37: =H23 -> 7.1165835 | I37: =I23 -> 45.305741 | J37: =J23 -> 121.65039 | K37: =K23 -> 185.49845 | L37: =L23 -> 286.52452 | ... Q37: =Q23 -> 683.6024
C38: Receipt from Licensee for salsforce costs | E38: =E24 -> 0 | F38: =F24 -> 0 | G38: =G24 -> 0 | H38: =H24 -> 15 | I38: =I24 -> 39 | J38: =J24 -> 64.5 | K38: =K24 -> 72 | L38: =L24 -> 72 | ... Q38: =Q24 -> 72
C39: US profit share | D39: =NPV(D51,E39:S39) -> 2766.5418 | H39: =H25 -> 5.5369466 | I39: =I25 -> 109.37204 | J39: =J25 -> 195.05696 | K39: =K25 -> 406.39516 | L39: =L25 -> 561.19358 | M39: =M25 -> 706.60705 | N39: =N25 -> 867.18845 | O39: =O25 -> 997.04424 | ... Q39: =Q25 -> 1230.5237
B40: Total Income | E40: =SUM(E36:E39) -> 150 | F40: =SUM(F36:F39) -> 35 | G40: =SUM(G36:G39) -> 0 | H40: =SUM(H36:H39) -> 82.65353 | I40: =SUM(I36:I39) -> 238.67779 | J40: =SUM(J36:J39) -> 706.20735 | K40: =SUM(K36:K39) -> 838.89362 | L40: =SUM(L36:L39) -> 919.7181 | ... Q40: =SUM(Q36:Q39) -> 1986.1261
C41: Royalties and milestone payable (University) | D41: =Project!D13 -> 0.04 | E41: =$D$41*E4 -> 0 | F41: =$D$41*F4 -> 0 | G41: =$D$41*G4 -> 0 | H41: =$D$41*H4 -> 2.8466334 | I41: =$D$41*I4 -> 17.76858 | J41: =$D$41*J4 -> 41.614398 | K41: =$D$41*K4 -> 74.374613 | L41: =$D$41*L4 -> 99.63113 | ... Q41: =$D$41*Q4 -> 198.9006
C42: Licensor supply profit | H42: =-COG!I64 -> -0.82257499 | I42: =-COG!J64 -> -4.9878794 | J42: =-COG!K64 -> -15.59633 | K42: =-COG!L64 -> -19.691287 | L42: =-COG!M64 -> -27.040128 | M42: =-COG!N64 -> -33.622368 | N42: =-COG!O64 -> -39.755019 | O42: =-COG!P64 -> -45.439837 | ... Q42: =-COG!R64 -> -54.472128
C43: R&D | E43: ='R&D'!I38 -> 2.45 | F43: ='R&D'!J38 -> 2.7 | G43: ='R&D'!K38 -> 3.35 | H43: ='R&D'!L38 -> 5.03164 | I43: ='R&D'!M38 -> 6.88467 | J43: ='R&D'!N38 -> 7.73486 | K43: ='R&D'!O38 -> 6.91063 | L43: ='R&D'!P38 -> 1.45472 | ... Q43: ='R&D'!U38 -> 0
C44: Sales & Marketing costs | H44: ='S&M'!H81 -> 10 | I44: ='S&M'!I81 -> 26 | J44: ='S&M'!J81 -> 43 | K44: ='S&M'!K81 -> 48 | L44: ='S&M'!L81 -> 48 | M44: ='S&M'!M81 -> 48 | N44: ='S&M'!N81 -> 48 | O44: ='S&M'!O81 -> 48 | ... Q44: ='S&M'!Q81 -> 48
C45: Administration | D45: 0 | E45: =$D$45*E39 -> 0 | F45: =$D$45*F39 -> 0 | G45: =$D$45*G39 -> 0 | H45: =$D$45*H39 -> 0 | I45: =$D$45*I39 -> 0 | J45: =$D$45*J39 -> 0 | K45: =$D$45*K39 -> 0 | L45: =$D$45*L39 -> 0 | ... Q45: =$D$45*Q39 -> 0
B46: Operating profit / EBITDA | E46: =E40-SUM(E41:E45) -> 147.55 | F46: =F40-SUM(F41:F45) -> 32.3 | G46: =G40-SUM(G41:G45) -> -3.35 | H46: =H40-SUM(H41:H45) -> 65.597832 | I46: =I40-SUM(I41:I45) -> 193.01241 | J46: =J40-SUM(J41:J45) -> 629.45443 | K46: =K40-SUM(K41:K45) -> 729.29966 | L46: =L40-SUM(L41:L45) -> 797.67237 | ... Q46: =Q40-SUM(Q41:Q45) -> 1793.6976
C47: Depreciation and amortisation | D47: Ignored
C48: Working capital movement | D48: Ignored
C49: Capital expenditure | D49: Ignored
B50: Cash flow | E50: =SUM(E46:E49) -> 147.55 | F50: =SUM(F46:F49) -> 32.3 | G50: =SUM(G46:G49) -> -3.35 | H50: =SUM(H46:H49) -> 65.597832 | I50: =SUM(I46:I49) -> 193.01241 | J50: =SUM(J46:J49) -> 629.45443 | K50: =SUM(K46:K49) -> 729.29966 | L50: =SUM(L46:L49) -> 797.67237 | ... Q50: =SUM(Q46:Q49) -> 1793.6976
B51: NPV incl terminal value excl sunk costs | D51: =Control!G45 -> 0.12 | E51: =NPV(D51,F50:R50)+E50 -> 3698.1527 | F51: % total | G51: =1-G31 -> 0.39306025 | H51: =NPV($D$31,F50:Q50)+E50 -> 3698.1527 | I51: to 2026 | M51: Terminal value | N51: =E51-H51 -> 0 | O51: =N51/E51 -> 0
A53: TOTAL PROJECT VALUATION excl sunk costs | E53: =E51+E31 -> 9408.6153 | H53: =H51+H31 -> 5989.899 | N53: =N51+N31 -> 3418.7163
C55: Total profit | E55: =E46+E26 -> -18.924655 | F55: =F46+F26 -> -56.540766 | G55: =G46+G26 -> -86.296869 | H55: =H46+H26 -> -111.05127 | I55: =I46+I26 -> 62.759946 | J55: =J46+J26 -> 344.04884 | K55: =K46+K26 -> 946.1669 | L55: =L46+L26 -> 1554.6797 | ... R55: =R46+R26 -> 14917.545
B57: NPV incl terminal value INCL sunk costs | D57: =Control!G45 -> 0.12 | E57: =NPV(D57,G82:R82)+F82 -> 3259.7318
B58: IRR incl terminal value INCL sunk costs | E58: =IRR(F82:P82) -> #NUM!
C61: Licensor COG + royalty % sales | H61: =H63+H72 -> 0.14623426 | I61: =I63+I72 -> 0.15813337 | J61: =J63+J72 -> 0.19188747 | K61: =K63+K72 -> 0.15271603 | L61: =L63+L72 -> 0.16931462 | M61: =M63+M72 -> 0.17830402 | N61: =N63+N72 -> 0.1838702 | O61: =O63+O72 -> 0.18784259 | ... Q61: =Q63+Q72 -> 0.1922494
C62: Total cost of goods | H62: =H7+H14 -> 3.2903 | I62: =I7+I14 -> 24.939397 | J62: =J7+J14 -> 77.981651 | K62: =K7+K14 -> 98.456435 | L62: =L7+L14 -> 135.20064 | M62: =M7+M14 -> 168.11184 | N62: =N7+N14 -> 198.77509 | O62: =O7+O14 -> 227.19918 | ... Q62: =Q7+Q14 -> 272.36064
C63: % of sales | H63: =H62/H66 -> 0.046234263 | I63: =I62/I66 -> 0.056142689 | J63: =J62/J66 -> 0.074956414 | K63: =K62/K66 -> 0.052951636 | L63: =L62/L66 -> 0.054280481 | M63: =M62/M66 -> 0.054839082 | N63: =N62/N66 -> 0.054679289 | O63: =O62/O66 -> 0.054911968 | ... Q63: =Q62/Q66 -> 0.054773216
A65: ROYALTY CALCULATION | D65: $m | E65: =E35 -> 2009 | F65: =F35 -> 2010 | G65: =G35 -> 2011 | H65: =H35 -> 2012 | I65: =I35 -> 2013 | J65: =J35 -> 2014 | K65: =K35 -> 2015 | L65: =L35 -> 2016 | ... Q65: =Q35 -> 2021
C66: Total sales | H66: =H6+H13 -> 71.165835 | I66: =I6+I13 -> 444.21451 | J66: =J6+J13 -> 1040.36 | K66: =K6+K13 -> 1859.3653 | L66: =L6+L13 -> 2490.7782 | M66: =M6+M13 -> 3065.548 | N66: =N6+N13 -> 3635.2904 | O66: =O6+O13 -> 4137.5167 | ... Q66: =Q6+Q13 -> 4972.515
C67: Sales < x | D67: =Control!F32 -> 400 | E67: =Control!G32 -> 0.1 | F67: x | H67: =IF(H66<$D67,(H66*$E67))+IF(H66>$D67,$D67*$E67) -> 7.1165835 | I67: =IF(I66<$D67,(I66*$E67))+IF(I66>$D67,$D67*$E67) -> 40 | J67: =IF(J66<$D67,(J66*$E67))+IF(J66>$D67,$D67*$E67) -> 40 | K67: =IF(K66<$D67,(K66*$E67))+IF(K66>$D67,$D67*$E67) -> 40 | L67: =IF(L66<$D67,(L66*$E67))+IF(L66>$D67,$D67*$E67) -> 40 | M67: =IF(M66<$D67,(M66*$E67))+IF(M66>$D67,$D67*$E67) -> 40 | N67: =IF(N66<$D67,(N66*$E67))+IF(N66>$D67,$D67*$E67) -> 40 | O67: =IF(O66<$D67,(O66*$E67))+IF(O66>$D67,$D67*$E67) -> 40 | ... Q67: =IF(Q66<$D67,(Q66*$E67))+IF(Q66>$D67,$D67*$E67) -> 40
C68: Sales > x < y | D68: =Control!F33 -> 800 | E68: =Control!G33 -> 0.12 | F68: y | H68: =IF(H66>$D67,H66<=$D68)*(H66-$D67)*$E68+IF(H66>$D68,($D68-$D67)*$E68) -> 0 | I68: =IF(I66>$D67,I66<=$D68)*(I66-$D67)*$E68+IF(I66>$D68,($D68-$D67)*$E68) -> 5.3057415 | J68: =IF(J66>$D67,J66<=$D68)*(J66-$D67)*$E68+IF(J66>$D68,($D68-$D67)*$E68) -> 48 | K68: =IF(K66>$D67,K66<=$D68)*(K66-$D67)*$E68+IF(K66>$D68,($D68-$D67)*$E68) -> 48 | L68: =IF(L66>$D67,L66<=$D68)*(L66-$D67)*$E68+IF(L66>$D68,($D68-$D67)*$E68) -> 48 | M68: =IF(M66>$D67,M66<=$D68)*(M66-$D67)*$E68+IF(M66>$D68,($D68-$D67)*$E68) -> 48 | N68: =IF(N66>$D67,N66<=$D68)*(N66-$D67)*$E68+IF(N66>$D68,($D68-$D67)*$E68) -> 48 | O68: =IF(O66>$D67,O66<=$D68)*(O66-$D67)*$E68+IF(O66>$D68,($D68-$D67)*$E68) -> 48 | ... Q68: =IF(Q66>$D67,Q66<=$D68)*(Q66-$D67)*$E68+IF(Q66>$D68,($D68-$D67)*$E68) -> 48
C69: Sales < y > z | D69: =Control!F34 -> 1200 | E69: =Control!G34 -> 0.14 | F69: z | H69: =IF(H66>$D68,H66<=$D69)*(H66-$D68)*$E69+IF(H66>$D69,(H66-$D68)*$E69) -> 0 | I69: =IF(I66>$D68,I66<=$D69)*(I66-$D68)*$E69+IF(I66>$D69,(I66-$D68)*$E69) -> 0 | J69: =IF(J66>$D68,J66<=$D69)*(J66-$D68)*$E69+IF(J66>$D69,($D69-$D68)*$E69) -> 33.650395 | K69: =IF(K66>$D68,K66<=$D69)*(K66-$D68)*$E69+IF(K66>$D69,($D69-$D68)*$E69) -> 56 | L69: =IF(L66>$D68,L66<=$D69)*(L66-$D68)*$E69+IF(L66>$D69,($D69-$D68)*$E69) -> 56 | M69: =IF(M66>$D68,M66<=$D69)*(M66-$D68)*$E69+IF(M66>$D69,($D69-$D68)*$E69) -> 56 | N69: =IF(N66>$D68,N66<=$D69)*(N66-$D68)*$E69+IF(N66>$D69,($D69-$D68)*$E69) -> 56 | O69: =IF(O66>$D68,O66<=$D69)*(O66-$D68)*$E69+IF(O66>$D69,($D69-$D68)*$E69) -> 56 | P69: =IF(P66>$D68,P66<=$D69)*(P66-$D68)*$E69+IF(P66>$D69,($D69-$D68)*$E69) -> 56 | Q69: =IF(Q66>$D68,Q66<=$D69)*(Q66-$D68)*$E69+IF(Q66>$D69,($D69-$D68)*$E69) -> 56
C70: Sales > z | D70: =Control!F35 -> 1600 | E70: =Control!G35 -> 0.16 | H70: =IF(H66>$D69,H66<=$D70)*(H66-$D69)*$E70+IF(H66>$D70,(H66-$D70)*$E70) -> 0 | I70: =IF(I66>$D69,I66<=$D70)*(I66-$D69)*$E70+IF(I66>$D70,(I66-$D70)*$E70) -> 0 | J70: =IF(J66>$D69,J66<=$D70)*(J66-$D69)*$E70+IF(J66>$D70,(J66-$D70)*$E70) -> 0 | K70: =IF(K66>$D69,K66<=$D70)*(K66-$D69)*$E70+IF(K66>$D70,(K66-$D70)*$E70) -> 41.498453 | L70: =IF(L66>$D69,L66<=$D70)*(L66-$D69)*$E70+IF(L66>$D70,(L66-$D70)*$E70) -> 142.52452 | M70: =IF(M66>$D69,M66<=$D70)*(M66-$D69)*$E70+IF(M66>$D70,(M66-$D70)*$E70) -> 234.48769 | N70: =IF(N66>$D69,N66<=$D70)*(N66-$D69)*$E70+IF(N66>$D70,(N66-$D70)*$E70) -> 325.64646 | O70: =IF(O66>$D69,O66<=$D70)*(O66-$D69)*$E70+IF(O66>$D70,(O66-$D70)*$E70) -> 406.00267 | ... Q70: =IF(Q66>$D69,Q66<=$D70)*(Q66-$D69)*$E70+IF(Q66>$D70,(Q66-$D70)*$E70) -> 539.6024
C71: Total royalties | H71: =SUM(H67:H70) -> 7.1165835 | I71: =SUM(I67:I70) -> 45.305741 | J71: =SUM(J67:J70) -> 121.65039 | K71: =SUM(K67:K70) -> 185.49845 | L71: =SUM(L67:L70) -> 286.52452 | M71: =SUM(M67:M70) -> 378.48769 | N71: =SUM(N67:N70) -> 469.64646 | O71: =SUM(O67:O70) -> 550.00267 | ... Q71: =SUM(Q67:Q70) -> 683.6024
C72: % of sales | H72: =H71/H66 -> 0.1 | I72: =I71/I66 -> 0.10199068 | J72: =J71/J66 -> 0.11693106 | K72: =K71/K66 -> 0.099764393 | L72: =L71/L66 -> 0.11503413 | M72: =M71/M66 -> 0.12346493 | N72: =N71/N66 -> 0.12919091 | O72: =O71/O66 -> 0.13293062 | ... Q72: =Q71/Q66 -> 0.13747619
A74: TOTAL VALUATION | D74: $m | E74: =E3 -> 2009 | F74: =F3 -> 2010 | G74: =G3 -> 2011 | H74: =H3 -> 2012 | I74: =I3 -> 2013 | J74: =J3 -> 2014 | K74: =K3 -> 2015 | L74: =L3 -> 2016 | ... Q74: =Q3 -> 2021
B75: Cash flow incl terminal value | D75: =E53 -> 9408.6153 | E75: =E30+E50 -> -18.924655 | F75: =F30+F50 -> -56.540766 | G75: =G30+G50 -> -86.296869 | H75: =H30+H50 -> -111.05127 | I75: =I30+I50 -> 62.759946 | J75: =J30+J50 -> 344.04884 | K75: =K30+K50 -> 946.1669 | L75: =L30+L50 -> 1554.6797 | ... R75: =R30+R50 -> 14917.545
B76: Project check | D76: =NPV(D77,F76:R76)+E76 -> 9302.5829 | E76: =Project!E25 -> -18.924655 | F76: =Project!F25 -> -56.540766 | G76: =Project!G25 -> -86.296869 | H76: =Project!H25 -> -111.87385 | I76: =Project!I25 -> 57.772067 | J76: =Project!J25 -> 328.45251 | K76: =Project!K25 -> 926.47561 | L76: =Project!L25 -> 1527.6396 | ... R76: =Project!R25 -> 14917.545
D77: 0.12 | E77: =E75-E76 -> 0 | F77: =F75-F76 -> 0 | G77: =G75-G76 -> 0 | H77: =H75-H76 -> 0.82257499 | I77: =I75-I76 -> 4.9878794 | J77: =J75-J76 -> 15.59633 | K77: =K75-K76 -> 19.691287 | L77: =L75-L76 -> 27.040128 | ... R77: =R75-R76 -> 0
A79: Licensor cash flow incl sunk costs undiscounted | E79: =E3 -> 2009 | F79: =F74 -> 2010 | G79: =G74 -> 2011 | H79: =H74 -> 2012 | I79: =I74 -> 2013 | J79: =J74 -> 2014 | K79: =K74 -> 2015 | L79: =L74 -> 2016 | M79: =M74 -> 2017 | ... Q79: =Q74 -> 2021
C80: Cash flow excl sunk costs | F80: =E50 -> 147.55 | G80: =F50 -> 32.3 | H80: =G50 -> -3.35 | I80: =H50 -> 65.597832 | J80: =I50 -> 193.01241 | K80: =J50 -> 629.45443 | L80: =K50 -> 729.29966 | M80: =L50 -> 797.67237 | ... P80: =O50 -> 1450.9861 | Q80: =Q50 -> 1793.6976 | R80: =R50 -> 0
C81: Sunk costs prior to deal | F81: =-'Lor Financials'!D44 -> -17.194
C82: Cash flow incl sunk costs | F82: =F80+F81 -> 130.356 | G82: =G80+G81 -> 32.3 | H82: =H80+H81 -> -3.35 | I82: =I80+I81 -> 65.597832 | J82: =J80+J81 -> 193.01241 | K82: =K80+K81 -> 629.45443 | L82: =L80+L81 -> 729.29966 | M82: =M80+M81 -> 797.67237 | ... R82: =R80+R81 -> 0
A84: Licensee working capital calculation | D84: Ratio | E84: =E79 -> 2009 | F84: =F79 -> 2010 | G84: =G79 -> 2011 | H84: =H79 -> 2012 | I84: =I79 -> 2013 | J84: =J79 -> 2014 | K84: =K79 -> 2015 | L84: =L79 -> 2016 | ... Q84: =Q79 -> 2021
B85: Receivables/debtors | D85: DSO | E85: 30 | F85: =F4/365*$E$85 -> 0 | G85: =G4/365*$E$85 -> 0 | H85: =H4/365*$E$85 -> 5.8492467 | I85: =I4/365*$E$85 -> 36.510782 | J85: =J4/365*$E$85 -> 85.509038 | K85: =K4/365*$E$85 -> 152.82455 | L85: =L4/365*$E$85 -> 204.7215 | M85: =M4/365*$E$85 -> 251.96285 | ... Q85: =Q4/365*$E$85 -> 408.69986
B86: Inventory/stock | D86: DOS | E86: 90 | F86: =(F7+F14)/365*$E$86 -> 0 | G86: =(G7+G14)/365*$E$86 -> 0 | H86: =(H7+H14)/365*$E$86 -> 0.81130684 | I86: =(I7+I14)/365*$E$86 -> 6.1494404 | J86: =(J7+J14)/365*$E$86 -> 19.228352 | K86: =(K7+K14)/365*$E$86 -> 24.276929 | L86: =(L7+L14)/365*$E$86 -> 33.337144 | M86: =(M7+M14)/365*$E$86 -> 41.452235 | ... Q86: =(Q7+Q14)/365*$E$86 -> 67.157418
B87: Payables/creditors | D87: DCO | E87: 30 | F87: =-F91/365*$E$87 -> -4.4252684 | G87: =-G91/365*$E$87 -> -6.8175509 | H87: =-H91/365*$E$87 -> -15.577367 | I87: =-I91/365*$E$87 -> -41.468021 | J87: =-J91/365*$E$87 -> -75.845252 | K87: =-K91/365*$E$87 -> -112.52397 | L87: =-L91/365*$E$87 -> -131.38934 | M87: =-M91/365*$E$87 -> -149.05734 | ... Q87: =-Q91/365*$E$87 -> -219.22615
B88: Year end working capital balance | F88: =F86+F85+F87 -> -4.4252684 | G88: =G86+G85+G87 -> -6.8175509 | H88: =H86+H85+H87 -> -8.9168139 | I88: =I86+I85+I87 -> 1.1922017 | J88: =J86+J85+J87 -> 28.892138 | K88: =K86+K85+K87 -> 64.577505 | L88: =L86+L85+L87 -> 106.6693 | M88: =M86+M85+M87 -> 144.35774 | ... Q88: =Q86+Q85+Q87 -> 256.63113
B89: Movement in working capital | F89: =D88-F88 -> 4.4252684 | G89: =E88-G88 -> 6.8175509 | H89: =G88-H88 -> 2.099263 | I89: =H88-I88 -> -10.109016 | J89: =I88-J88 -> -27.699937 | K89: =J88-K88 -> -35.685367 | L89: =K88-L88 -> -42.091799 | M89: =L88-M88 -> -37.688439 | N89: =M88-N88 -> -33.629552 | O89: =N88-O88 -> -31.107924 | ... Q89: =P88-Q88 -> -17.777399
C90: % of income | I90: =I89/I4 -> -0.022757058 | J90: =J89/J4 -> -0.026625339 | K90: =K89/K4 -> -0.01919223 | L90: =L89/L4 -> -0.016899055 | M90: =M89/M4 -> -0.012294193 | N90: =N89/N4 -> -0.0092508573 | O90: =O89/O4 -> -0.007518501 | P90: =P89/P4 -> -0.0063978388 | Q90: =Q89/Q4 -> -0.0035751323
C91: operating costs | F91: =F8+F10+F15+F17+F19+F20+F23+F24+F25 -> 53.840766 | G91: =G8+G10+G15+G17+G19+G20+G23+G24+G25 -> 82.946869 | H91: =H8+H10+H15+H17+H19+H20+H23+H24+H25 -> 189.52464 | I91: =I8+I10+I15+I17+I19+I20+I23+I24+I25 -> 504.52758 | J91: =J8+J10+J15+J17+J19+J20+J23+J24+J25 -> 922.7839 | K91: =K8+K10+K15+K17+K19+K20+K23+K24+K25 -> 1369.0417 | L91: =L8+L10+L15+L17+L19+L20+L23+L24+L25 -> 1598.5703 | M91: =M8+M10+M15+M17+M19+M20+M23+M24+M25 -> 1813.531 | ... Q91: =Q8+Q10+Q15+Q17+Q19+Q20+Q23+Q24+Q25 -> 2667.2515
A92: Licensor working capital calculation | D92: Ratio | E92: =E84 -> 2009 | F92: =F84 -> 2010 | G92: =G84 -> 2011 | H92: =H84 -> 2012 | I92: =I84 -> 2013 | J92: =J84 -> 2014 | K92: =K84 -> 2015 | L92: =L84 -> 2016 | ... Q92: =Q84 -> 2021
B93: Receivables/debtors | D93: DSO | E93: 30 | F93: =F40/365*$E$93 -> 2.8767123 | G93: =G40/365*$E$93 -> 0 | H93: =H40/365*$E$93 -> 6.7934408 | I93: =I40/365*$E$93 -> 19.617352 | J93: =J40/365*$E$93 -> 58.04444 | K93: =K40/365*$E$93 -> 68.95016 | L93: =L40/365*$E$93 -> 75.593268 | M93: =M40/365*$E$93 -> 95.103677 | ... Q93: =Q40/365*$E$93 -> 163.24324
B94: Inventory/stock | D94: DOS | E94: 90
B95: Payables/creditors | D95: DCO | E95: 30 | F95: =-(F45+F44+F43+F41)/365*$E$95 -> -0.22191781 | G95: =-(G45+G44+G43+G41)/365*$E$95 -> -0.27534247 | H95: =-(H45+H44+H43+H41)/365*$E$95 -> -1.4694471 | I95: =-(I45+I44+I43+I41)/365*$E$95 -> -4.1632809 | J95: =-(J45+J44+J43+J41)/365*$E$95 -> -7.59035 | K95: =-(K45+K44+K43+K41)/365*$E$95 -> -10.626184 | L95: =-(L45+L44+L43+L41)/365*$E$95 -> -12.253631 | M95: =-(M45+M44+M43+M41)/365*$E$95 -> -14.175926 | ... Q95: =-(Q45+Q44+Q43+Q41)/365*$E$95 -> -20.2932
B96: Year end working capital balance | F96: =F94+F93+F95 -> 2.6547945 | G96: =G94+G93+G95 -> -0.27534247 | H96: =H94+H93+H95 -> 5.3239937 | I96: =I94+I93+I95 -> 15.454071 | J96: =J94+J93+J95 -> 50.45409 | K96: =K94+K93+K95 -> 58.323976 | L96: =L94+L93+L95 -> 63.339637 | M96: =M94+M93+M95 -> 80.927752 | ... Q96: =Q94+Q93+Q95 -> 142.95004
B97: Movement in working capital | F97: =E96-F96 -> -2.6547945 | G97: =F96-G96 -> 2.930137 | H97: =G96-H96 -> -5.5993362 | I97: =H96-I96 -> -10.130078 | J97: =I96-J96 -> -35.000019 | K97: =J96-K96 -> -7.8698858 | L97: =K96-L96 -> -5.0156608 | M97: =L96-M96 -> -17.588115 | ... Q97: =P96-Q96 -> -10.922556
C98: % of income | H98: =H97/H40 -> -0.067744671 | I98: =I97/I40 -> -0.042442482 | J98: =J97/J40 -> -0.049560541 | K98: =K97/K40 -> -0.0093812679 | L98: =L97/L40 -> -0.0054534763 | M98: =M97/M40 -> -0.015200238 | N98: =N97/N40 -> -0.013411046 | O98: =O97/O40 -> -0.0096986979 | ... Q98: =Q97/Q40 -> -0.0054994275

Sheet Lor Financials
A1: Licensor Financial History & Forecast $m
A2: LICENSOR P&L | D2: =E2-1 -> 2005 | E2: =F2-1 -> 2006 | F2: =G2-1 -> 2007 | G2: =H2-1 -> 2008 | H2: =Control!M5 -> 2009 | I2: =H2+1 -> 2010 | J2: =I2+1 -> 2011 | K2: =J2+1 -> 2012 | L2: =K2+1 -> 2013 | M2: =L2+1 -> 2014 | N2: =M2+1 -> 2015
D3: Actual | H3: Forecast
C4: License fee and other revenues | G4: 225 | H4: =Control!M40+Control!M41 -> 150 | I4: =Control!N40+Control!N41 -> 35 | J4: =Control!O40+Control!O41 -> 0 | K4: =Control!P40+Control!P41 -> 62.116583 | L4: =Control!Q40+Control!Q41 -> 90.305741 | M4: =Control!R40+Control!R41 -> 446.65039 | N4: =Control!S40+Control!S41 -> 360.49845
C5: R&D income / payments
C6: Total Revenues | D6: 0 | E6: 0 | F6: 0 | G6: =G4+G5 -> 225 | H6: =H4+H5 -> 150 | I6: =I4+I5 -> 35 | J6: =J4+J5 -> 0 | K6: =K4+K5 -> 62.116583 | L6: =L4+L5 -> 90.305741 | M6: =M4+M5 -> 446.65039 | N6: =N4+N5 -> 360.49845
B7: Costs and expenses
C8: R&D direct excl prolutamide | D8: 3.077 | E8: 5.384 | F8: 11.469 | G8: 31.391 | H8: 56.6 | I8: 44.585 | J8: 26.204 | K8: 21.354 | L8: 36.14 | M8: 61.063 | N8: 59.071
C9: R&D direct prolutamide | D9: 0.261 | E9: 3.02025 | F9: 2.61825 | G9: 8.8445 | H9: ='Lee & Lor'!E43 -> 2.45 | I9: ='Lee & Lor'!F43 -> 2.7 | J9: ='Lee & Lor'!G43 -> 3.35 | K9: ='Lee & Lor'!H43 -> 5.03164 | L9: ='Lee & Lor'!I43 -> 6.88467 | M9: ='Lee & Lor'!J43 -> 7.73486 | N9: ='Lee & Lor'!K43 -> 6.91063
C10: R&D indirect | D10: 1.934 | E10: 3.42 | F10: 9.311 | G10: 14.659 | H10: 4.1 | I10: 4.189 | J10: 4.893 | K10: 7.188 | L10: 9.736 | M10: 19.889 | N10: 26.86
C11: G&A incl in R&D | D11: 3.143 | E11: 4.321 | F11: 10.364 | G11: 21.865 | H11: 29 | I11: 23 | J11: 13 | K11: 10 | L11: 18 | M11: 30 | N11: 30
C12: Total Costs | D12: =SUM(D8:D11) -> 8.415 | E12: =SUM(E8:E11) -> 16.14525 | F12: =SUM(F8:F11) -> 33.76225 | G12: =SUM(G8:G11) -> 76.7595 | H12: =SUM(H8:H11) -> 92.15 | I12: =SUM(I8:I11) -> 74.474 | J12: =SUM(J8:J11) -> 47.447 | K12: =SUM(K8:K11) -> 43.57364 | ... N12: =SUM(N8:N11) -> 122.84163
B13: Operating Profit / Loss | D13: =D6-D12 -> -8.415 | E13: =E6-E12 -> -16.14525 | F13: =F6-F12 -> -33.76225 | G13: =G6-G12 -> 148.2405 | H13: =H6-H12 -> 57.85 | I13: =I6-I12 -> -39.474 | J13: =J6-J12 -> -47.447 | K13: =K6-K12 -> 18.542943 | ... N13: =N6-N12 -> 237.65682
C14: Interest and other income | D14: 1.401 | E14: -0.785 | F14: -2.022 | G14: -1.712 | H14: -1
B15: Net profit / (loss) before tax | D15: =D13-D14 -> -9.816 | E15: =E13-E14 -> -15.36025 | F15: =F13-F14 -> -31.74025 | G15: =G13-G14 -> 149.9525 | H15: =H13-H14 -> 58.85 | I15: =I13-I14 -> -39.474 | J15: =J13-J14 -> -47.447 | K15: =K13-K14 -> 18.542943 | ... N15: =N13-N14 -> 237.65682
C16: Tax | D16: 0 | E16: 0 | F16: 0 | G16: 0 | H16: 0 | I16: 0 | J16: 0 | K16: 0
B17: Net loss after tax | D17: =D15-D16 -> -9.816 | E17: =E15-E16 -> -15.36025 | F17: =F15-F16 -> -31.74025 | G17: =G15-G16 -> 149.9525 | H17: =H15-H16 -> 58.85 | I17: =I15-I16 -> -39.474 | J17: =J15-J16 -> -47.447 | K17: =K15-K16 -> 18.542943 | ... N17: =N15-N16 -> 237.65682
C18: Cumulative | D18: =D17 -> -9.816 | E18: =E17+D18 -> -25.17625 | F18: =F17+E18 -> -56.9165 | G18: =G17+F18 -> 93.036 | H18: =H17+G18 -> 151.886 | I18: =I17+H18 -> 112.412 | J18: =J17+I18 -> 64.965 | K18: =K17+J18 -> 83.507943 | L18: =L17+K18 -> 103.05301 | ... N18: =N17+M18 -> 668.67337
A20: LICENSOR CASH FLOW | D20: =D2 -> 2005 | E20: =E2 -> 2006 | F20: =F2 -> 2007 | G20: =G2 -> 2008 | H20: =H2 -> 2009 | I20: =I2 -> 2010 | J20: =J2 -> 2011 | K20: =K2 -> 2012 | ... N20: =N2 -> 2015
B21: Net profit / (loss) before tax | D21: =D17 -> -9.816 | E21: =E17 -> -15.36025 | F21: =F17 -> -31.74025 | G21: =G17 -> 149.9525 | H21: =H17 -> 58.85 | I21: =I17 -> -39.474 | J21: =J17 -> -47.447 | K21: =K17 -> 18.542943 | ... N21: =N17 -> 237.65682
C22: Non cash items | D22: 1.1295 | E22: 2.52393 | F22: 5.903 | G22: 8.4 | H22: =-59.298+69.25 -> 9.952 | I22: 13 | J22: 14 | K22: 35 | L22: 54 | M22: 12 | N22: 2
C23: Working capital movement | D23: 1.086 | E23: 0.205 | F23: 2.482 | G23: =216.234-212.42 -> 3.814 | H23: =106.466-110 -> -3.534 | I23: -2 | J23: 5 | K23: 5 | L23: -54 | M23: -34 | N23: -24
C24: Cash from operating activity | D24: =D21+D22+D23 -> -7.6005 | E24: =E21+E22+E23 -> -12.63132 | F24: =F21+F22+F23 -> -23.35525 | G24: =G21+G22+G23 -> 162.1665 | H24: =H21+H22+H23 -> 65.268 | I24: =I21+I22+I23 -> -28.474 | J24: =J21+J22+J23 -> -28.447 | K24: =K21+K22+K23 -> 58.542943 | ... N24: =N21+N22+N23 -> 215.65682
C25: Capital expenditure | D25: -8.268 | E25: -34.276 | F25: 40.931 | G25: -149.546 | H25: -72.568
B26: Cash utilised | D26: =D24+D25 -> -15.8685 | E26: =E24+E25 -> -46.90732 | F26: =F24+F25 -> 17.57575 | G26: =G24+G25 -> 12.6205 | H26: =H24+H25 -> -7.3 | I26: =I24+I25 -> -28.474 | J26: =J24+J25 -> -28.447 | K26: =K24+K25 -> 58.542943 | ... N26: =N24+N25 -> 215.65682
C27: Funds raised | D27: 9.785 | E27: 46.972 | F27: 21.036 | G27: 15.57 | H27: 66.162
B28: Net increase / decrease in cash | D28: =D26+D27 -> -6.0835 | E28: =E26+E27 -> 0.06468 | F28: =F26+F27 -> 38.61175 | G28: =G26+G27 -> 28.1905 | H28: =H26+H27 -> 58.862 | I28: =I26+I27 -> -28.474 | J28: =J26+J27 -> -28.447 | K28: =K26+K27 -> 58.542943 | ... N28: =N26+N27 -> 215.65682
B29: Opening cash balance | D29: 10.671 | E29: =D30 -> 4.5875 | F29: =E30 -> 4.65218 | G29: =F30 -> 43.26393 | H29: =G30 -> 71.45443 | I29: =H30 -> 130.31643 | J29: =I30 -> 101.84243 | K29: =J30 -> 73.39543 | L29: =K30 -> 131.93837 | ... N29: =M30 -> 457.44698
B30: Closing cash balance | D30: =D28+D29 -> 4.5875 | E30: =E28+E29 -> 4.65218 | F30: =F28+F29 -> 43.26393 | G30: =G28+G29 -> 71.45443 | H30: =H28+H29 -> 130.31643 | I30: =I28+I29 -> 101.84243 | J30: =J28+J29 -> 73.39543 | K30: =K28+K29 -> 131.93837 | ... N30: =N28+N29 -> 673.1038
A32: SHARES | D32: =D20 -> 2005 | E32: =E20 -> 2006 | F32: =F20 -> 2007 | G32: =G20 -> 2008 | H32: =H20 -> 2009 | I32: =I20 -> 2010 | J32: =J20 -> 2011 | K32: =K20 -> 2012 | ... N32: =N20 -> 2015
B33: Total number of shares | D33: 13.937 | E33: 24.248 | F33: 27.932 | G33: 29.478 | H33: 32.094 | I33: 69.148 | J33: 71.464 | K33: 146.95 | L33: 150.33 | M33: 153.86 | N33: 160.35
C34: Public price | D34: 0.61 | E34: 3.9 | F34: 3.6 | G34: 3.72 | H34: 9.41 | I34: 3.79 | J34: 11.6 | K34: 25.58 | L34: 31.91 | M34: 49.81 | N34: 48.34
C35: Company valuation $m | D35: =D33*D34 -> 8.50157 | E35: =E33*E34 -> 94.5672 | F35: =F33*F34 -> 100.5552 | G35: =G33*G34 -> 109.65816 | H35: =H33*H34 -> 302.00454 | I35: =I33*I34 -> 262.07092 | J35: =J33*J34 -> 828.9824 | K35: =K33*K34 -> 3758.981 | ... N35: =N33*N34 -> 7751.319
A38: FUND RAISING
B39: Ordinary shares issued m | D39: 5.635 | E39: 5.215 | F39: =(265.43+758.12)/1000 -> 1.02355 | G39: 1.1295 | H39: 3.1625
B40: Share price $ | D40: 2 | E40: =E41/E39 -> 9.6356663 | F40: =F41/F39 -> 20.761077 | G40: =G41/G39 -> 13.811421 | H40: =H41/H39 -> 19.72996
B41: Amount raised / gross proceeds | D41: =D39*D40 -> 11.27 | E41: 50.25 | F41: 21.25 | G41: 15.6 | H41: 62.396
B42: Net amount raised from share issues | D42: 9.764 | E42: =E41-3.499 -> 46.751 | F42: 20.799 | G42: 14.911 | H42: 62.059
C44: Sunk prolutamide costs | D44: =SUM(D9:H9) -> 17.194

Sheet Benchmarks
A1: Date | B1: Licensor | C1: Licensee | D1: Product | E1: Indication | F1: Devt Phase at deal | G1: Territory | H1: Upfront $m | I1: Equity $m | J1: Devt and reg Milestones $m | K1: Sales Milestones $m | L1: Headline $m | M1: Royalty
A2: Licensor deal
A3: 39692 | B3: Minerva | C3: Pfizer | D3: Dimebon | E3: Alzheimers | F3: Early phase 3 | G3: Global option co-promote US | H3: 225 | J3: 500 | K3: ND | L3: 725+ | M3: Profit share US 40% Minerva
M4: Tiered royalties outside US
A5: Licensee deal
A6: 39539 | B6: CoMentis | C6: Atlas | D6: beta secretase inhib | E6: Alzheimers | F6: End Phase 1 | G6: Global option co-promote US | H6: 80 | I6: 20 | J6: 660 | K6: ND | L6: 760+ | M6: Profit share US
M7: Royalties outside US
A8: Oncology deals
A9: 40057 | B9: Algeta | C9: Bayer | D9: alpharadin (radium 223) | E9: HRPC bone metastases | F9: Phase 3 | G9: Global option co-promote US | H9: 61 | L9: 800 | M9: Profit share US | N9: Euros | O9: 42.5 | P9: 860
M10: Tiered double digit outside US
A12: 39661 | B12: PDL Biopharma | C12: BMS | D12: elotuzumab | E12: multiple myeloma | F12: Phase 1 | G12: Global | H12: 30 | J12: 480 | K12: 200 | L12: 710 | M12: Profit share US
M13: Royalties outside US
A15: 39600 | B15: Astex | C15: Janssen | D15: FGFR inhibitors | E15: cancer | F15: Pre clinical | G15: Global | H15: 37 | J15: 500+ | L15: 537+ | M15: Tiered double digit
A17: 39142 | B17: Oxford BioMedica | C17: Sanofi | D17: cancer vaccine | E17: Renal cancer | F17: Phase 3 | G17: Global option co-promote US Europe | H17: 32 | J17: 517 | L17: 549 | N17: Euros | O17: 29 | P17: 470
